[
  {
    "lead_id": "1389148375757476",
    "created_time": "2026-02-05T13:46:06+0000",
    "form_name": "META Philippines 02/2026",
    "campaign_id": "120237959815840775",
    "campaign_name": "Supy_Facebook_Philippines_Meta",
    "adset_id": "120237959815830775",
    "adset_name": "Meta_Philippines_Facebook_Leadgen_Enterprise_Broad",
    "ad_id": "120237959815820775",
    "ad_name": "Interest_Philippines_Facebook_Lead_Ad",
    "first_name": "Sinan",
    "last_name": "Batur",
    "email": null,
    "phone_number": "+639189020436",
    "company_name": "S&l Finefoods",
    "country": "Philippines",
    "custom_fields": {
      "work_email": "sinan@s-lfinefoods.com"
    }
  },
  {
    "lead_id": "1922412761698219",
    "created_time": "2026-02-05T10:27:50+0000",
    "form_name": "META Philippines 02/2026",
    "campaign_id": "120237959815840775",
    "campaign_name": "Supy_Facebook_Philippines_Meta",
    "adset_id": "120237959815830775",
    "adset_name": "Meta_Philippines_Facebook_Leadgen_Enterprise_Broad",
    "ad_id": "120237959815820775",
    "ad_name": "Interest_Philippines_Facebook_Lead_Ad",
    "first_name": "Pocholo Miguel",
    "last_name": "Kanapi",
    "email": null,
    "phone_number": "+639178432598",
    "company_name": "Takoboba",
    "country": "Philippines",
    "custom_fields": {
      "work_email": "ukiyotavern@gmail.com"
    }
  },
  {
    "lead_id": "929505622857268",
    "created_time": "2026-02-04T19:45:48+0000",
    "form_name": "META Philippines 02/2026",
    "campaign_id": "120237959815840775",
    "campaign_name": "Supy_Facebook_Philippines_Meta",
    "adset_id": "120237959815830775",
    "adset_name": "Meta_Philippines_Facebook_Leadgen_Enterprise_Broad",
    "ad_id": "120237959815820775",
    "ad_name": "Interest_Philippines_Facebook_Lead_Ad",
    "first_name": "Jannessy",
    "last_name": "Arrienda",
    "email": null,
    "phone_number": "+639267341442",
    "company_name": "Ylopo",
    "country": "Philippines",
    "custom_fields": {
      "work_email": "juansroastbeef@gmail.com"
    }
  },
  {
    "lead_id": "934638745913160",
    "created_time": "2026-02-05T11:31:15+0000",
    "form_name": "META GCC 02/2026",
    "campaign_id": "120208097408850775",
    "campaign_name": "Supy_Facebook_GCC_LAL_Leadgen",
    "adset_id": "120209603184100775",
    "adset_name": "LAL_Admin_GCC_Facebook_NA",
    "ad_id": "120209603184110775",
    "ad_name": "LAL_Admin_GCC_Facebook_Video_Ad",
    "first_name": "Warith",
    "last_name": "Kharusi",
    "email": null,
    "phone_number": "+96899330089",
    "company_name": "AlSafwa & Partners",
    "country": null,
    "custom_fields": {
      "work_email": "warith.kharusi@alsafwa.co.om"
    }
  },
  {
    "lead_id": "1420374363022410",
    "created_time": "2026-02-05T15:34:53+0000",
    "form_name": "META Cambodia 5 Loc 02/2026",
    "campaign_id": "120237787403190775",
    "campaign_name": "Supy_Facebook_Cambodia_Meta",
    "adset_id": "120237787403170775",
    "adset_name": "Meta_Cambodia_Facebook_Leadgen_Broad",
    "ad_id": "120237787403180775",
    "ad_name": "Interest_Cambodia_Facebook_Lead_Ad",
    "first_name": "Hēā",
    "last_name": "Lŷ Kō",
    "email": null,
    "phone_number": "+85510707319",
    "company_name": "Hea ko",
    "country": "Cambodia",
    "custom_fields": {
      "work_email": "seeyou17339@icloud.com"
    }
  },
  {
    "lead_id": "1208367248136898",
    "created_time": "2026-02-05T07:59:15+0000",
    "form_name": "META Cambodia 5 Loc 02/2026",
    "campaign_id": "120237787403190775",
    "campaign_name": "Supy_Facebook_Cambodia_Meta",
    "adset_id": "120237787403170775",
    "adset_name": "Meta_Cambodia_Facebook_Leadgen_Broad",
    "ad_id": "120237787403180775",
    "ad_name": "Interest_Cambodia_Facebook_Lead_Ad",
    "first_name": "Sok",
    "last_name": "Chea",
    "email": null,
    "phone_number": "+85515550565",
    "company_name": "LKP Company",
    "country": "Cambodia",
    "custom_fields": {
      "work_email": "Chuonsokchea166@gmail.com"
    }
  },
  {
    "lead_id": "1559743651909158",
    "created_time": "2026-02-05T00:48:32+0000",
    "form_name": "META Cambodia 5 Loc 02/2026",
    "campaign_id": "120237787403190775",
    "campaign_name": "Supy_Facebook_Cambodia_Meta",
    "adset_id": "120237787403170775",
    "adset_name": "Meta_Cambodia_Facebook_Leadgen_Broad",
    "ad_id": "120237787403180775",
    "ad_name": "Interest_Cambodia_Facebook_Lead_Ad",
    "first_name": "Poly",
    "last_name": "Lov",
    "email": null,
    "phone_number": "+19727501997",
    "company_name": "Poly Pizza",
    "country": "Cambodia",
    "custom_fields": {
      "work_email": "Sonomotpl@yahoo.com"
    }
  },
  {
    "lead_id": "1417947443134738",
    "created_time": "2026-02-04T19:30:56+0000",
    "form_name": "META Cambodia 5 Loc 02/2026",
    "campaign_id": "120237787403190775",
    "campaign_name": "Supy_Facebook_Cambodia_Meta",
    "adset_id": "120237787403170775",
    "adset_name": "Meta_Cambodia_Facebook_Leadgen_Broad",
    "ad_id": "120237787403180775",
    "ad_name": "Interest_Cambodia_Facebook_Lead_Ad",
    "first_name": "Mich",
    "last_name": "Long",
    "email": null,
    "phone_number": "+85586738335",
    "company_name": "Phnom Penh",
    "country": "Cambodia",
    "custom_fields": {
      "work_email": "visophin951@gmail.com"
    }
  },
  {
    "lead_id": "1405049934652335",
    "created_time": "2026-02-04T19:09:17+0000",
    "form_name": "META Cambodia 5 Loc 02/2026",
    "campaign_id": "120237787403190775",
    "campaign_name": "Supy_Facebook_Cambodia_Meta",
    "adset_id": "120237787403170775",
    "adset_name": "Meta_Cambodia_Facebook_Leadgen_Broad",
    "ad_id": "120237787403180775",
    "ad_name": "Interest_Cambodia_Facebook_Lead_Ad",
    "first_name": "Eang",
    "last_name": "sok",
    "email": null,
    "phone_number": "+855975564217",
    "company_name": "ប្រភព៖ Kampuchea Thmey Daily\n https://search.app/ha15H",
    "country": "Cambodia",
    "custom_fields": {
      "work_email": "sokeangroth80@gmail.com"
    }
  },
  {
    "lead_id": "1236961535028240",
    "created_time": "2026-02-05T17:28:46+0000",
    "form_name": "META Taiwan 02/2026",
    "campaign_id": "120237782273820775",
    "campaign_name": "Supy_Facebook_Taiwan_Meta",
    "adset_id": "120237782273810775",
    "adset_name": "Meta_Taiwan_Facebook_Leadgen_Broad",
    "ad_id": "120237782273830775",
    "ad_name": "Interest_ Macau_Facebook_Lead_Ad",
    "first_name": "Mathias",
    "last_name": "Sinamenye",
    "email": null,
    "phone_number": "+886972890074",
    "company_name": "長榮大學管樂團 Chang Jung Christian University Symphonic Band",
    "country": "Taiwan",
    "custom_fields": {
      "work_email": "mathiassinamenye677@gmail.com"
    }
  },
  {
    "lead_id": "3840709402889726",
    "created_time": "2026-02-05T05:32:00+0000",
    "form_name": "META Singapore 02/2026",
    "campaign_id": "120237739636990775",
    "campaign_name": "Supy_Facebook_Singapore_Meta",
    "adset_id": "120237739637120775",
    "adset_name": "Meta_Singapore_Facebook_Leadgen_Broad",
    "ad_id": "120237739637060775",
    "ad_name": "Interest_Singapore _Facebook_Lead_Ad",
    "first_name": "Alvin",
    "last_name": "Lin",
    "email": null,
    "phone_number": "+19294948064",
    "company_name": "SOULFUL VENTURES",
    "country": "Singapore",
    "custom_fields": {
      "work_email": "alvinlin@mushaequity.com"
    }
  },
  {
    "lead_id": "1027814637071875",
    "created_time": "2026-02-05T15:15:57+0000",
    "form_name": "META Morocco 02/2026",
    "campaign_id": "120208097408850775",
    "campaign_name": "Supy_Facebook_GCC_LAL_Leadgen",
    "adset_id": "120237560109240775",
    "adset_name": "Facebook_Morroco_Broad",
    "ad_id": "120237560109230775",
    "ad_name": "LAL_Admin_ Morocco_Facebook_Video_Ad",
    "first_name": "Achraaf",
    "last_name": "ElMeknasi",
    "email": null,
    "phone_number": "+212655773448",
    "company_name": "Tétouan",
    "country": "Morocco",
    "custom_fields": {
      "work_email": "ashraafelmkna@gamail.com"
    }
  },
  {
    "lead_id": "2970294666492929",
    "created_time": "2026-02-05T14:23:03+0000",
    "form_name": "META Morocco 02/2026",
    "campaign_id": "120208097408850775",
    "campaign_name": "Supy_Facebook_GCC_LAL_Leadgen",
    "adset_id": "120237560109240775",
    "adset_name": "Facebook_Morroco_Broad",
    "ad_id": "120237560109230775",
    "ad_name": "LAL_Admin_ Morocco_Facebook_Video_Ad",
    "first_name": "Mohamed",
    "last_name": "Aamar",
    "email": null,
    "phone_number": "+212709200030",
    "company_name": "FOOD CHEF AAMAR",
    "country": "Morocco",
    "custom_fields": {
      "work_email": "chefaamar@gmail.com"
    }
  },
  {
    "lead_id": "1634431501304704",
    "created_time": "2026-02-05T12:25:42+0000",
    "form_name": "META Morocco 02/2026",
    "campaign_id": "120208097408850775",
    "campaign_name": "Supy_Facebook_GCC_LAL_Leadgen",
    "adset_id": "120237560109240775",
    "adset_name": "Facebook_Morroco_Broad",
    "ad_id": "120237560109230775",
    "ad_name": "LAL_Admin_ Morocco_Facebook_Video_Ad",
    "first_name": "Najat",
    "last_name": "Belkaide",
    "email": null,
    "phone_number": "+212786013463",
    "company_name": "Najat",
    "country": "Morocco",
    "custom_fields": {
      "work_email": "Najatbelkaid@gmail.ma"
    }
  },
  {
    "lead_id": "1240256088313698",
    "created_time": "2026-02-05T10:44:30+0000",
    "form_name": "META Morocco 02/2026",
    "campaign_id": "120208097408850775",
    "campaign_name": "Supy_Facebook_GCC_LAL_Leadgen",
    "adset_id": "120237560109240775",
    "adset_name": "Facebook_Morroco_Broad",
    "ad_id": "120237560109230775",
    "ad_name": "LAL_Admin_ Morocco_Facebook_Video_Ad",
    "first_name": "Mounir Gahlimi",
    "last_name": "Ftarti",
    "email": null,
    "phone_number": "+212723702083",
    "company_name": "Tabinal",
    "country": "Morocco",
    "custom_fields": {
      "work_email": "lminouralex@gmail.com"
    }
  },
  {
    "lead_id": "1448955060280286",
    "created_time": "2026-02-05T07:09:35+0000",
    "form_name": "META Morocco 02/2026",
    "campaign_id": "120208097408850775",
    "campaign_name": "Supy_Facebook_GCC_LAL_Leadgen",
    "adset_id": "120237560109240775",
    "adset_name": "Facebook_Morroco_Broad",
    "ad_id": "120237560109230775",
    "ad_name": "LAL_Admin_ Morocco_Facebook_Video_Ad",
    "first_name": "Hichame",
    "last_name": "Asbane",
    "email": null,
    "phone_number": "+212614670812",
    "company_name": "Marrakech",
    "country": "Morocco",
    "custom_fields": {
      "work_email": "asbanehichame7408@gmail.com"
    }
  },
  {
    "lead_id": "1995734514706314",
    "created_time": "2026-02-05T02:12:46+0000",
    "form_name": "META Morocco 02/2026",
    "campaign_id": "120208097408850775",
    "campaign_name": "Supy_Facebook_GCC_LAL_Leadgen",
    "adset_id": "120237560109240775",
    "adset_name": "Facebook_Morroco_Broad",
    "ad_id": "120237560109230775",
    "ad_name": "LAL_Admin_ Morocco_Facebook_Video_Ad",
    "first_name": "Mohamed",
    "last_name": "Idihya",
    "email": null,
    "phone_number": "+212607422096",
    "company_name": "Casablanca",
    "country": "Morocco",
    "custom_fields": {
      "work_email": "idihyamohamedidihya@gmail.com"
    }
  },
  {
    "lead_id": "1520345302393781",
    "created_time": "2026-02-04T23:51:38+0000",
    "form_name": "META Morocco 02/2026",
    "campaign_id": "120208097408850775",
    "campaign_name": "Supy_Facebook_GCC_LAL_Leadgen",
    "adset_id": "120237560109240775",
    "adset_name": "Facebook_Morroco_Broad",
    "ad_id": "120237560109230775",
    "ad_name": "LAL_Admin_ Morocco_Facebook_Video_Ad",
    "first_name": "spirit_of_morocco",
    "last_name": "abderrahim",
    "email": null,
    "phone_number": "+212667966545",
    "company_name": "SPIRIT of Morocco",
    "country": "Morocco",
    "custom_fields": {
      "work_email": "info83service@gmail.com"
    }
  },
  {
    "lead_id": "25765604446426495",
    "created_time": "2026-02-04T22:07:09+0000",
    "form_name": "META Morocco 02/2026",
    "campaign_id": "120208097408850775",
    "campaign_name": "Supy_Facebook_GCC_LAL_Leadgen",
    "adset_id": "120237560109240775",
    "adset_name": "Facebook_Morroco_Broad",
    "ad_id": "120237560109230775",
    "ad_name": "LAL_Admin_ Morocco_Facebook_Video_Ad",
    "first_name": "fatima ben",
    "last_name": "abbou",
    "email": null,
    "phone_number": "+212650689088",
    "company_name": "Fari 1234",
    "country": "Morocco",
    "custom_fields": {
      "work_email": "benabbouf4@gmail.com"
    }
  },
  {
    "lead_id": "1413564483810980",
    "created_time": "2026-02-05T16:23:23+0000",
    "form_name": "META Hong Kong 02/2026",
    "campaign_id": "120227305650640775",
    "campaign_name": "Supy_Facebook_HK_MY_LAL_Leadgen",
    "adset_id": "120227305650710775",
    "adset_name": "LAL_Admin_HK_MY_Facebook_Leadgen",
    "ad_id": "120227305650700775",
    "ad_name": "LAL_Admin_HK_MY _Facebook_Lead_Ad",
    "first_name": "𝔸𝕊𝟟",
    "last_name": "Shah",
    "email": null,
    "phone_number": "0132100011",
    "company_name": "Raaji Group of Companies (RAAJI Silk Palace)",
    "country": "Hong Kong",
    "custom_fields": {
      "work_email": "azmanmohamed0302@gmail.com"
    }
  },
  {
    "lead_id": "1609360870314343",
    "created_time": "2026-02-05T06:10:00+0000",
    "form_name": "META New Zealand 02/2026",
    "campaign_id": "120207533114190775",
    "campaign_name": "Supy_Facebook_AUS_LAL_Leadgen",
    "adset_id": "120219950339920775",
    "adset_name": "LAL_Admin_NZ_Facebook_Lead",
    "ad_id": "120219950339930775",
    "ad_name": "LAL_Admin_NZ_Facebook_Lead_Ad",
    "first_name": "Cass",
    "last_name": "Houkamau",
    "email": null,
    "phone_number": "+6421614904",
    "company_name": "IHC",
    "country": "New Zealand",
    "custom_fields": {
      "work_email": "casshoukamau7@gmail.com"
    }
  },
  {
    "lead_id": "1516618140469014",
    "created_time": "2026-02-05T17:42:13+0000",
    "form_name": "META United Kingdom 02/2026",
    "campaign_id": "120211055502090775",
    "campaign_name": "Supy_Facebook_Ireland_Leadgen",
    "adset_id": "120211091399920775",
    "adset_name": "LAL_LAL_UK_Facebook",
    "ad_id": "120211091399910775",
    "ad_name": "LAL_Deal_UK_Facebook_Video_Ad",
    "first_name": "Swaylee",
    "last_name": "Hawkins",
    "email": null,
    "phone_number": "+447835784895",
    "company_name": "Evolve",
    "country": "United Kingdom",
    "custom_fields": {
      "work_email": "Evolve@Evolve.com"
    }
  },
  {
    "lead_id": "1217993017128282",
    "created_time": "2026-02-04T21:21:59+0000",
    "form_name": "META United Kingdom 02/2026",
    "campaign_id": "120211055502090775",
    "campaign_name": "Supy_Facebook_Ireland_Leadgen",
    "adset_id": "120211091399920775",
    "adset_name": "LAL_LAL_UK_Facebook",
    "ad_id": "120211091399910775",
    "ad_name": "LAL_Deal_UK_Facebook_Video_Ad",
    "first_name": "Nikita Reid -",
    "last_name": "Lyle",
    "email": null,
    "phone_number": "+447872946509",
    "company_name": "Cafe 19",
    "country": "United Kingdom",
    "custom_fields": {
      "work_email": "Renikita853@gmail.com"
    }
  },
  {
    "lead_id": "882696534390656",
    "created_time": "2026-02-05T03:56:32+0000",
    "form_name": "META Australia HQ 02/2026",
    "campaign_id": "120207533114190775",
    "campaign_name": "Supy_Facebook_AUS_LAL_Leadgen",
    "adset_id": "120211091446780775",
    "adset_name": "LAL_Admin_AUS_Facebook_Lead",
    "ad_id": "120211091446770775",
    "ad_name": "LAL_Admin_AUS_Facebook_Lead_Ad",
    "first_name": "Anthony",
    "last_name": "Altmann",
    "email": null,
    "phone_number": "+614369292593",
    "company_name": "Mowers",
    "country": "Australia",
    "custom_fields": {
      "work_email": "anthonyjoel.altmann@gmail.com"
    }
  }
]