[
  {
    "lead_id": "1992105911374698",
    "created_time": "2026-02-13T17:37:10+0000",
    "form_name": "META Ireland 02/2026",
    "campaign_id": null,
    "campaign_name": null,
    "adset_id": null,
    "adset_name": null,
    "ad_id": null,
    "ad_name": null,
    "first_name": "test",
    "last_name": "test",
    "email": null,
    "phone_number": "+918123837123",
    "company_name": "meta form singapore",
    "country": "Ireland",
    "custom_fields": {
      "work_email": "Pavan+test541@gmail.com"
    }
  },
  {
    "lead_id": "2414451478991741",
    "created_time": "2026-02-13T03:51:46+0000",
    "form_name": "META Philippines 02/2026",
    "campaign_id": "120237959815840775",
    "campaign_name": "Supy_Facebook_Philippines_Meta",
    "adset_id": "120237959815830775",
    "adset_name": "Meta_Philippines_Facebook_Leadgen_Enterprise_Broad",
    "ad_id": "120237959815820775",
    "ad_name": "Interest_Philippines_Facebook_Lead_Ad",
    "first_name": "george",
    "last_name": "caballes",
    "email": null,
    "phone_number": "+639950832734",
    "company_name": "georhose bookkeeping and accounting services",
    "country": "Philippines",
    "custom_fields": {
      "work_email": "georgecaballes51@gmail.com"
    }
  },
  {
    "lead_id": "1257697742925882",
    "created_time": "2026-02-13T10:07:25+0000",
    "form_name": "META Laos 5 Loc 02/2026",
    "campaign_id": "120237828724960775",
    "campaign_name": "Supy_Facebook_Laos_Meta",
    "adset_id": "120237828724980775",
    "adset_name": "Meta_Laos_Facebook_Leadgen_Broad",
    "ad_id": "120237828724970775",
    "ad_name": "Interest_Laos_Facebook_Lead_Ad",
    "first_name": "ອ້າຍສີນ",
    "last_name": "ບີນບໍ່ໄດ້",
    "email": null,
    "phone_number": "+8562058080605",
    "company_name": "ເຮັດໄຮ່ເຮັດນາ",
    "country": "Laos",
    "custom_fields": {
      "work_email": "luihotmail3344@gmail.com"
    }
  },
  {
    "lead_id": "1619981052350497",
    "created_time": "2026-02-12T22:37:41+0000",
    "form_name": "META Laos 5 Loc 02/2026",
    "campaign_id": "120237828724960775",
    "campaign_name": "Supy_Facebook_Laos_Meta",
    "adset_id": "120237828724980775",
    "adset_name": "Meta_Laos_Facebook_Leadgen_Broad",
    "ad_id": "120237828724970775",
    "ad_name": "Interest_Laos_Facebook_Lead_Ad",
    "first_name": "ณัฐพล",
    "last_name": "ท้าวมา",
    "email": null,
    "phone_number": "+8562098181005",
    "company_name": "บริษัท วัดใจคน",
    "country": "Laos",
    "custom_fields": {
      "work_email": "natthaphonpotphay@gmail.com"
    }
  },
  {
    "lead_id": "1497662265308557",
    "created_time": "2026-02-13T15:21:39+0000",
    "form_name": "META Cambodia 5 Loc 02/2026",
    "campaign_id": "120237787403190775",
    "campaign_name": "Supy_Facebook_Cambodia_Meta",
    "adset_id": "120237787403170775",
    "adset_name": "Meta_Cambodia_Facebook_Leadgen_Broad",
    "ad_id": "120237787403180775",
    "ad_name": "Interest_Cambodia_Facebook_Lead_Ad",
    "first_name": "Ah Nech",
    "last_name": "Kpc",
    "email": null,
    "phone_number": "+855964308784",
    "company_name": "Facebook",
    "country": "Cambodia",
    "custom_fields": {
      "work_email": "salatyty97@gmail.com"
    }
  },
  {
    "lead_id": "887339094265059",
    "created_time": "2026-02-12T21:46:02+0000",
    "form_name": "META Cambodia 5 Loc 02/2026",
    "campaign_id": "120237787403190775",
    "campaign_name": "Supy_Facebook_Cambodia_Meta",
    "adset_id": "120237787403170775",
    "adset_name": "Meta_Cambodia_Facebook_Leadgen_Broad",
    "ad_id": "120237787403180775",
    "ad_name": "Interest_Cambodia_Facebook_Lead_Ad",
    "first_name": "LAISOKHA",
    "last_name": "Sohka",
    "email": null,
    "phone_number": "+855965827685",
    "company_name": "ឃុំកណ្ដាលឃុំត្នោតភ្ជុំស្រុកក្រគរខេត្តពោធិ៍សាត់",
    "country": "Cambodia",
    "custom_fields": {
      "work_email": "laisokha@gmfikhrn.com"
    }
  },
  {
    "lead_id": "1267304865320529",
    "created_time": "2026-02-12T22:52:05+0000",
    "form_name": "META Macau 02/2026",
    "campaign_id": "120237780732490775",
    "campaign_name": "Supy_Facebook_Macau_Meta",
    "adset_id": "120237780732480775",
    "adset_name": "Meta_Macau_Facebook_Leadgen_Broad",
    "ad_id": "120237780732500775",
    "ad_name": "Interest_Macau_Facebook_Lead_Ad",
    "first_name": "jiandong",
    "last_name": "pan",
    "email": null,
    "phone_number": "+33751336783",
    "company_name": "jiandong pan",
    "country": "Macau",
    "custom_fields": {
      "work_email": "jiandongpan9@gmail.com"
    }
  },
  {
    "lead_id": "4182944785353735",
    "created_time": "2026-02-13T16:20:16+0000",
    "form_name": "META Morocco 02/2026",
    "campaign_id": "120208097408850775",
    "campaign_name": "Supy_Facebook_GCC_LAL_Leadgen",
    "adset_id": "120237560109240775",
    "adset_name": "Facebook_Morroco_Broad",
    "ad_id": "120237560109230775",
    "ad_name": "LAL_Admin_ Morocco_Facebook_Video_Ad",
    "first_name": "Zouine",
    "last_name": "Ahmed",
    "email": null,
    "phone_number": "+212621988831",
    "company_name": "ملوسه طنجه",
    "country": "Morocco",
    "custom_fields": {
      "work_email": "ahmedzouine590@gmail.com"
    }
  },
  {
    "lead_id": "1557381628699201",
    "created_time": "2026-02-13T14:03:02+0000",
    "form_name": "META Morocco 02/2026",
    "campaign_id": "120208097408850775",
    "campaign_name": "Supy_Facebook_GCC_LAL_Leadgen",
    "adset_id": "120237560109240775",
    "adset_name": "Facebook_Morroco_Broad",
    "ad_id": "120237560109230775",
    "ad_name": "LAL_Admin_ Morocco_Facebook_Video_Ad",
    "first_name": "Otmane",
    "last_name": "bensghir otmane",
    "email": null,
    "phone_number": "+212669248118",
    "company_name": "la modernité",
    "country": "Morocco",
    "custom_fields": {
      "work_email": "bensghirotmane.21@gmail.com"
    }
  },
  {
    "lead_id": "26365856696355687",
    "created_time": "2026-02-13T09:05:11+0000",
    "form_name": "META Morocco 02/2026",
    "campaign_id": "120208097408850775",
    "campaign_name": "Supy_Facebook_GCC_LAL_Leadgen",
    "adset_id": "120237560109240775",
    "adset_name": "Facebook_Morroco_Broad",
    "ad_id": "120237560109230775",
    "ad_name": "LAL_Admin_ Morocco_Facebook_Video_Ad",
    "first_name": "boufi",
    "last_name": "Salman",
    "email": null,
    "phone_number": "+212699110043",
    "company_name": "Maroc",
    "country": "Morocco",
    "custom_fields": {
      "work_email": "Salmanboufi@gmail.com"
    }
  },
  {
    "lead_id": "1937217607226575",
    "created_time": "2026-02-13T03:14:27+0000",
    "form_name": "META Morocco 02/2026",
    "campaign_id": "120208097408850775",
    "campaign_name": "Supy_Facebook_GCC_LAL_Leadgen",
    "adset_id": "120237560109240775",
    "adset_name": "Facebook_Morroco_Broad",
    "ad_id": "120237560109230775",
    "ad_name": "LAL_Admin_ Morocco_Facebook_Video_Ad",
    "first_name": "Loko",
    "last_name": "Ilyass",
    "email": null,
    "phone_number": "+212608206778",
    "company_name": "24",
    "country": "Morocco",
    "custom_fields": {
      "work_email": "ilyassloko554@gmail.com"
    }
  },
  {
    "lead_id": "25878096108483542",
    "created_time": "2026-02-13T02:11:29+0000",
    "form_name": "META Morocco 02/2026",
    "campaign_id": "120208097408850775",
    "campaign_name": "Supy_Facebook_GCC_LAL_Leadgen",
    "adset_id": "120237560109240775",
    "adset_name": "Facebook_Morroco_Broad",
    "ad_id": "120237560109230775",
    "ad_name": "LAL_Admin_ Morocco_Facebook_Video_Ad",
    "first_name": "Said",
    "last_name": "Bendaoud",
    "email": null,
    "phone_number": "+212659501140",
    "company_name": "fatima bendaoud",
    "country": "Morocco",
    "custom_fields": {
      "work_email": "saidbendaoudsaidbendaoud@gmail.com"
    }
  },
  {
    "lead_id": "882779444729594",
    "created_time": "2026-02-13T07:21:14+0000",
    "form_name": "META United Kingdom 02/2026",
    "campaign_id": "120211055502090775",
    "campaign_name": "Supy_Facebook_Ireland_Leadgen",
    "adset_id": "120211091399920775",
    "adset_name": "LAL_LAL_UK_Facebook",
    "ad_id": "120211091399910775",
    "ad_name": "LAL_Deal_UK_Facebook_Video_Ad",
    "first_name": "nial",
    "last_name": "pollitt",
    "email": null,
    "phone_number": "+447716743389",
    "company_name": "Really Useful Box Company",
    "country": "United Kingdom",
    "custom_fields": {
      "work_email": "warlordnial101@aol.com"
    }
  },
  {
    "lead_id": "1390728952269779",
    "created_time": "2026-02-13T01:17:05+0000",
    "form_name": "META United Kingdom 02/2026",
    "campaign_id": "120211055502090775",
    "campaign_name": "Supy_Facebook_Ireland_Leadgen",
    "adset_id": "120237266135990775",
    "adset_name": "LAL_Target_UK_Facebook",
    "ad_id": "120237266135980775",
    "ad_name": "LAL_Target_UK_Facebook_Video_Ad",
    "first_name": "Josh",
    "last_name": "Parmar",
    "email": null,
    "phone_number": "+447957592594",
    "company_name": "Prohibition  Chester",
    "country": "United Kingdom",
    "custom_fields": {
      "work_email": "Prohibitionchester@gmail.com"
    }
  }
]