[
  {
    "lead_id": "195026226444",
    "lead_link": "https://app.hubspot.com/contacts/9423176/record/0-1/195026226444",
    "createdate": "2026-01-21T19:26:03Z",
    "hs_v2_date_entered_marketingqualifiedlead": "2026-01-21T19:32:33.327Z",
    "hs_v2_date_entered_salesqualifiedlead": "2026-03-02T00:21:35.698Z",
    "hs_v2_date_entered_opportunity": "2026-03-02T00:21:37.250Z",
    "firstname": "Shams-i",
    "lastname": "Power",
    "email": "shamsi.rock@gmail.com",
    "phone": "+6421478995",
    "jobtitle": null,
    "company": "Re.",
    "country": "New Zealand",
    "number_of_locations": 2,
    "lifecyclestage": "opportunity",
    "hs_lead_status": "Qualified",
    "hs_analytics_source": "PAID_SOCIAL",
    "hs_analytics_source_data_1": "Facebook",
    "hs_analytics_source_data_2": "supy_facebook_aus_lal_leadgen",
    "new_lead_source": "Marketing",
    "utm_source": null,
    "utm_medium": null,
    "utm_campaign": null,
    "utm_content": null,
    "deal_id": "57093682194",
    "deal_link": "https://app.hubspot.com/contacts/9423176/record/0-3/57093682194",
    "deal_name": "Re. Union",
    "deal_createdate": "2026-03-02T00:21:32.612Z",
    "deal_stage": "Under Negotiation",
    "deal_amount": 440,
    "deal_currency_code": "NZD",
    "deal_amount_usd": null,
    "number_of_branches": 2
  },
  {
    "lead_id": "205072121452",
    "lead_link": "https://app.hubspot.com/contacts/9423176/record/0-1/205072121452",
    "createdate": "2026-02-24T15:05:47Z",
    "hs_v2_date_entered_marketingqualifiedlead": "2026-02-24T15:16:51.518Z",
    "hs_v2_date_entered_salesqualifiedlead": "2026-03-02T00:38:44.183Z",
    "hs_v2_date_entered_opportunity": "2026-03-03T06:16:29.621Z",
    "firstname": "Edmund",
    "lastname": "Sanchez",
    "email": "docedmund68@gmail.com",
    "phone": "+639176763002",
    "jobtitle": null,
    "company": "The Food Project",
    "country": "Philippines",
    "number_of_locations": 2,
    "lifecyclestage": "opportunity",
    "hs_lead_status": "Qualified",
    "hs_analytics_source": "PAID_SOCIAL",
    "hs_analytics_source_data_1": "Facebook",
    "hs_analytics_source_data_2": "supy_facebook_philippines_meta",
    "new_lead_source": "Marketing",
    "utm_source": null,
    "utm_medium": null,
    "utm_campaign": null,
    "utm_content": null,
    "deal_id": "58566879751",
    "deal_link": "https://app.hubspot.com/contacts/9423176/record/0-3/58566879751",
    "deal_name": "The Food Project Inc",
    "deal_createdate": "2026-03-02T00:38:42.189Z",
    "deal_stage": "Proposal Sent",
    "deal_amount": 397,
    "deal_currency_code": "USD",
    "deal_amount_usd": 397,
    "number_of_branches": 2
  },
  {
    "lead_id": "203964388418",
    "lead_link": "https://app.hubspot.com/contacts/9423176/record/0-1/203964388418",
    "createdate": "2026-02-19T22:33:20Z",
    "hs_v2_date_entered_marketingqualifiedlead": "2026-02-19T22:40:02.913Z",
    "hs_v2_date_entered_salesqualifiedlead": "2026-03-02T05:35:56.567Z",
    "hs_v2_date_entered_opportunity": "2026-03-13T00:55:55.286Z",
    "firstname": "Worachat",
    "lastname": "Tantibankool",
    "email": "thai-riffic@hotmail.com",
    "phone": "+61451962459",
    "jobtitle": null,
    "company": "Thai-Riffic Mildura",
    "country": "Australia",
    "number_of_locations": 2,
    "lifecyclestage": "opportunity",
    "hs_lead_status": "Qualified",
    "hs_analytics_source": "PAID_SOCIAL",
    "hs_analytics_source_data_1": "Facebook",
    "hs_analytics_source_data_2": "supy_facebook_aus_lal_leadgen",
    "new_lead_source": "Marketing",
    "utm_source": null,
    "utm_medium": null,
    "utm_campaign": null,
    "utm_content": null,
    "deal_id": "57307667550",
    "deal_link": "https://app.hubspot.com/contacts/9423176/record/0-3/57307667550",
    "deal_name": "Thai-Riffic",
    "deal_createdate": "2026-03-02T05:35:56.042Z",
    "deal_stage": "Demo Run",
    "deal_amount": 900,
    "deal_currency_code": "AUD",
    "deal_amount_usd": null,
    "number_of_branches": 2
  },
  {
    "lead_id": "206549498700",
    "lead_link": "https://app.hubspot.com/contacts/9423176/record/0-1/206549498700",
    "createdate": "2025-05-03T03:01:47Z",
    "hs_v2_date_entered_marketingqualifiedlead": "2026-03-02T08:10:10.106Z",
    "hs_v2_date_entered_salesqualifiedlead": "2026-03-03T00:45:08.076Z",
    "hs_v2_date_entered_opportunity": null,
    "firstname": "Ian",
    "lastname": "Lindsay",
    "email": "imlindsay1979@gmail.com",
    "phone": "+642102527570",
    "jobtitle": "Owner/CEO",
    "company": "Www.biggiespizza.co.nz",
    "country": "New Zealand",
    "number_of_locations": 2,
    "lifecyclestage": "salesqualifiedlead",
    "hs_lead_status": "Qualified",
    "hs_analytics_source": "PAID_SOCIAL",
    "hs_analytics_source_data_1": "Facebook",
    "hs_analytics_source_data_2": "supy_facebook_aus_lal_leadgen",
    "new_lead_source": "Marketing",
    "utm_source": null,
    "utm_medium": null,
    "utm_campaign": null,
    "utm_content": null,
    "deal_id": "57396908447",
    "deal_link": "https://app.hubspot.com/contacts/9423176/record/0-3/57396908447",
    "deal_name": "Biggies Pizza",
    "deal_createdate": "2026-03-03T00:45:07.292Z",
    "deal_stage": "Closed/Lost",
    "deal_amount": 458,
    "deal_currency_code": "NZD",
    "deal_amount_usd": null,
    "number_of_branches": 2
  },
  {
    "lead_id": "204248237101",
    "lead_link": "https://app.hubspot.com/contacts/9423176/record/0-1/204248237101",
    "createdate": "2026-02-20T22:19:20Z",
    "hs_v2_date_entered_marketingqualifiedlead": "2026-02-20T22:29:30.055Z",
    "hs_v2_date_entered_salesqualifiedlead": "2026-03-03T14:13:37.104Z",
    "hs_v2_date_entered_opportunity": "2026-03-05T11:21:10.757Z",
    "firstname": "Lee",
    "lastname": "Landau",
    "email": "lee@s-grp.co.uk",
    "phone": "+447794444006",
    "jobtitle": null,
    "company": "S group",
    "country": "United Kingdom",
    "number_of_locations": 10,
    "lifecyclestage": "opportunity",
    "hs_lead_status": "Qualified",
    "hs_analytics_source": "PAID_SOCIAL",
    "hs_analytics_source_data_1": "Facebook",
    "hs_analytics_source_data_2": "supy_facebook_uk_lal_leadgen",
    "new_lead_source": "Marketing",
    "utm_source": null,
    "utm_medium": null,
    "utm_campaign": null,
    "utm_content": null,
    "deal_id": "57447168347",
    "deal_link": "https://app.hubspot.com/contacts/9423176/record/0-3/57447168347",
    "deal_name": "Ranch",
    "deal_createdate": "2026-03-03T14:13:36.285Z",
    "deal_stage": "Delayed/Deferred",
    "deal_amount": 150,
    "deal_currency_code": "GBP",
    "deal_amount_usd": null,
    "number_of_branches": 10
  },
  {
    "lead_id": "191966487625",
    "lead_link": "https://app.hubspot.com/contacts/9423176/record/0-1/191966487625",
    "createdate": "2026-01-11T02:37:37Z",
    "hs_v2_date_entered_marketingqualifiedlead": "2026-01-11T02:44:02.433Z",
    "hs_v2_date_entered_salesqualifiedlead": "2026-03-04T23:54:10.369Z",
    "hs_v2_date_entered_opportunity": "2026-03-19T22:48:37.077Z",
    "firstname": "Raphaelexp",
    "lastname": "ExtonPery",
    "email": "jollygoodmelbourne@gmail.com",
    "phone": "",
    "jobtitle": "Owner",
    "company": "JollyGood",
    "country": "Australia",
    "number_of_locations": 3,
    "lifecyclestage": "opportunity",
    "hs_lead_status": "Qualified",
    "hs_analytics_source": "PAID_SOCIAL",
    "hs_analytics_source_data_1": "Facebook",
    "hs_analytics_source_data_2": "supy_facebook_aus_lal_leadgen",
    "new_lead_source": "Marketing",
    "utm_source": null,
    "utm_medium": null,
    "utm_campaign": null,
    "utm_content": null,
    "deal_id": "57539474833",
    "deal_link": "https://app.hubspot.com/contacts/9423176/record/0-3/57539474833",
    "deal_name": "JollyGood",
    "deal_createdate": "2026-03-04T23:54:09.748Z",
    "deal_stage": "Demo Run",
    "deal_amount": 900,
    "deal_currency_code": "AUD",
    "deal_amount_usd": null,
    "number_of_branches": 3
  },
  {
    "lead_id": "206991069752",
    "lead_link": "https://app.hubspot.com/contacts/9423176/record/0-1/206991069752",
    "createdate": "2026-03-04T14:48:14Z",
    "hs_v2_date_entered_marketingqualifiedlead": "2026-03-04T14:55:01.434Z",
    "hs_v2_date_entered_salesqualifiedlead": "2026-03-05T03:51:03.642Z",
    "hs_v2_date_entered_opportunity": "2026-03-11T22:30:41.608Z",
    "firstname": "Peter",
    "lastname": "Even",
    "email": "operation@peppina.asia",
    "phone": "+66633261101",
    "jobtitle": null,
    "company": "Pizza31",
    "country": "Thailand",
    "number_of_locations": 2,
    "lifecyclestage": "opportunity",
    "hs_lead_status": "Qualified",
    "hs_analytics_source": "PAID_SOCIAL",
    "hs_analytics_source_data_1": "Facebook",
    "hs_analytics_source_data_2": "supy_facebook_thailand_meta",
    "new_lead_source": "Marketing",
    "utm_source": null,
    "utm_medium": null,
    "utm_campaign": null,
    "utm_content": null,
    "deal_id": "57539477761",
    "deal_link": "https://app.hubspot.com/contacts/9423176/record/0-3/57539477761",
    "deal_name": "Peppina at Bluport",
    "deal_createdate": "2026-03-05T03:51:02.854Z",
    "deal_stage": "Demo Run",
    "deal_amount": 240,
    "deal_currency_code": "USD",
    "deal_amount_usd": 240,
    "number_of_branches": 2
  },
  {
    "lead_id": "206142519646",
    "lead_link": "https://app.hubspot.com/contacts/9423176/record/0-1/206142519646",
    "createdate": "2026-03-01T04:16:30Z",
    "hs_v2_date_entered_marketingqualifiedlead": "2026-03-01T04:23:17.791Z",
    "hs_v2_date_entered_salesqualifiedlead": "2026-03-09T04:31:51.471Z",
    "hs_v2_date_entered_opportunity": "2026-03-09T04:31:55.161Z",
    "firstname": "Tracy",
    "lastname": "Wong",
    "email": "tracy@mamamishk.com",
    "phone": "+85260553311",
    "jobtitle": null,
    "company": "Mam amis",
    "country": "Hong Kong",
    "number_of_locations": 2,
    "lifecyclestage": "opportunity",
    "hs_lead_status": "Qualified",
    "hs_analytics_source": "PAID_SOCIAL",
    "hs_analytics_source_data_1": "Facebook",
    "hs_analytics_source_data_2": "supy_facebook_hk_my_lal_leadgen",
    "new_lead_source": "Marketing",
    "utm_source": null,
    "utm_medium": null,
    "utm_campaign": null,
    "utm_content": null,
    "deal_id": "57784058916",
    "deal_link": "https://app.hubspot.com/contacts/9423176/record/0-3/57784058916",
    "deal_name": "MâmAmis",
    "deal_createdate": "2026-03-09T04:31:50.917Z",
    "deal_stage": "Demo Run",
    "deal_amount": 199,
    "deal_currency_code": "USD",
    "deal_amount_usd": 199,
    "number_of_branches": 2
  },
  {
    "lead_id": "206866469731",
    "lead_link": "https://app.hubspot.com/contacts/9423176/record/0-1/206866469731",
    "createdate": "2026-03-03T22:56:35Z",
    "hs_v2_date_entered_marketingqualifiedlead": "2026-03-03T23:07:28.628Z",
    "hs_v2_date_entered_salesqualifiedlead": "2026-03-09T21:56:39.483Z",
    "hs_v2_date_entered_opportunity": "2026-03-10T00:54:58.413Z",
    "firstname": "Eddy",
    "lastname": "Lee",
    "email": "edmond@lmegroup.com.au",
    "phone": "+61426228822",
    "jobtitle": null,
    "company": "LME Group",
    "country": "Australia",
    "number_of_locations": 6,
    "lifecyclestage": "opportunity",
    "hs_lead_status": "Qualified",
    "hs_analytics_source": "PAID_SOCIAL",
    "hs_analytics_source_data_1": "Facebook",
    "hs_analytics_source_data_2": "supy_facebook_aus_lal_leadgen",
    "new_lead_source": "Marketing",
    "utm_source": null,
    "utm_medium": null,
    "utm_campaign": null,
    "utm_content": null,
    "deal_id": "57830759513",
    "deal_link": "https://app.hubspot.com/contacts/9423176/record/0-3/57830759513",
    "deal_name": "LME Group Sydney",
    "deal_createdate": "2026-03-09T21:56:38.963Z",
    "deal_stage": "Proposal Sent",
    "deal_amount": 994,
    "deal_currency_code": "AUD",
    "deal_amount_usd": null,
    "number_of_branches": 6
  },
  {
    "lead_id": "205297987707",
    "lead_link": "https://app.hubspot.com/contacts/9423176/record/0-1/205297987707",
    "createdate": "2026-02-25T13:44:35Z",
    "hs_v2_date_entered_marketingqualifiedlead": "2026-02-25T13:47:39.016Z",
    "hs_v2_date_entered_salesqualifiedlead": "2026-03-09T22:14:31.473Z",
    "hs_v2_date_entered_opportunity": null,
    "firstname": "Jason",
    "lastname": "Pope",
    "email": "jason@dallas.sg",
    "phone": "+6594236622",
    "jobtitle": "Director",
    "company": "Dallas Singapore",
    "country": "Singapore",
    "number_of_locations": 2,
    "lifecyclestage": "salesqualifiedlead",
    "hs_lead_status": "Qualified",
    "hs_analytics_source": "PAID_SOCIAL",
    "hs_analytics_source_data_1": "Facebook",
    "hs_analytics_source_data_2": "supy_facebook_singapore_meta",
    "new_lead_source": "Marketing",
    "utm_source": null,
    "utm_medium": null,
    "utm_campaign": null,
    "utm_content": null,
    "deal_id": "57830142063",
    "deal_link": "https://app.hubspot.com/contacts/9423176/record/0-3/57830142063",
    "deal_name": "Dallas Singapore",
    "deal_createdate": "2026-03-09T22:14:30.696Z",
    "deal_stage": "Demo Booked",
    "deal_amount": 300,
    "deal_currency_code": "USD",
    "deal_amount_usd": 300,
    "number_of_branches": 2
  },
  {
    "lead_id": "211123144040",
    "lead_link": "https://app.hubspot.com/contacts/9423176/record/0-1/211123144040",
    "createdate": "2025-11-29T20:14:58Z",
    "hs_v2_date_entered_marketingqualifiedlead": "2026-03-08T07:28:01.734Z",
    "hs_v2_date_entered_salesqualifiedlead": "2026-03-10T02:52:34.447Z",
    "hs_v2_date_entered_opportunity": "2026-03-10T02:52:34.448Z",
    "firstname": "Hamid",
    "lastname": "Naseem",
    "email": "hnrcnaseem@yahoo.com",
    "phone": "+85252661476",
    "jobtitle": "Business Owner",
    "company": "Al-Abdullah",
    "country": "Hong Kong",
    "number_of_locations": 4,
    "lifecyclestage": "customer",
    "hs_lead_status": "Customer",
    "hs_analytics_source": "PAID_SOCIAL",
    "hs_analytics_source_data_1": "Facebook",
    "hs_analytics_source_data_2": "supy_facebook_hk_my_lal_leadgen",
    "new_lead_source": "Marketing",
    "utm_source": null,
    "utm_medium": null,
    "utm_campaign": null,
    "utm_content": null,
    "deal_id": "57830763950",
    "deal_link": "https://app.hubspot.com/contacts/9423176/record/0-3/57830763950",
    "deal_name": "Al-Abdullah Ltd.",
    "deal_createdate": "2026-03-10T02:52:29.411Z",
    "deal_stage": "Closed/Won",
    "deal_amount": 300,
    "deal_currency_code": "USD",
    "deal_amount_usd": 300,
    "number_of_branches": 4
  },
  {
    "lead_id": "208129747719",
    "lead_link": "https://app.hubspot.com/contacts/9423176/record/0-1/208129747719",
    "createdate": "2026-03-09T20:09:19Z",
    "hs_v2_date_entered_marketingqualifiedlead": "2026-03-09T20:13:30.517Z",
    "hs_v2_date_entered_salesqualifiedlead": "2026-03-10T04:10:41.267Z",
    "hs_v2_date_entered_opportunity": "2026-03-13T04:10:32.352Z",
    "firstname": "Mildred",
    "lastname": "Prats",
    "email": "mprats@hawkerchanph.com",
    "phone": "+639175647831",
    "jobtitle": null,
    "company": "Global Roast Food Corp",
    "country": "Philippines",
    "number_of_locations": 19,
    "lifecyclestage": "opportunity",
    "hs_lead_status": "Qualified",
    "hs_analytics_source": "PAID_SOCIAL",
    "hs_analytics_source_data_1": "Facebook",
    "hs_analytics_source_data_2": "supy_facebook_philippines_meta",
    "new_lead_source": "Marketing",
    "utm_source": null,
    "utm_medium": null,
    "utm_campaign": null,
    "utm_content": null,
    "deal_id": "57830147366",
    "deal_link": "https://app.hubspot.com/contacts/9423176/record/0-3/57830147366",
    "deal_name": "Global Roast Food Corp",
    "deal_createdate": "2026-03-10T04:10:40.613Z",
    "deal_stage": "Proposal Sent",
    "deal_amount": 2071,
    "deal_currency_code": "USD",
    "deal_amount_usd": 2071,
    "number_of_branches": 19
  },
  {
    "lead_id": "208180658027",
    "lead_link": "https://app.hubspot.com/contacts/9423176/record/0-1/208180658027",
    "createdate": "2026-03-10T00:41:20Z",
    "hs_v2_date_entered_marketingqualifiedlead": "2026-03-10T00:47:54.524Z",
    "hs_v2_date_entered_salesqualifiedlead": "2026-03-10T06:02:33.931Z",
    "hs_v2_date_entered_opportunity": "2026-03-18T21:52:01.195Z",
    "firstname": "Sam",
    "lastname": "Matthews",
    "email": "info@nomadbeachclubphuket.com",
    "phone": "+66824900373",
    "jobtitle": "Owner",
    "company": "Goat",
    "country": "Thailand",
    "number_of_locations": 2,
    "lifecyclestage": "opportunity",
    "hs_lead_status": "Qualified",
    "hs_analytics_source": "PAID_SOCIAL",
    "hs_analytics_source_data_1": "Facebook",
    "hs_analytics_source_data_2": "supy_facebook_thailand_meta",
    "new_lead_source": "Marketing",
    "utm_source": null,
    "utm_medium": null,
    "utm_campaign": null,
    "utm_content": null,
    "deal_id": "57830540728",
    "deal_link": "https://app.hubspot.com/contacts/9423176/record/0-3/57830540728",
    "deal_name": "Nomad Beach Club Phuket",
    "deal_createdate": "2026-03-10T06:02:33.347Z",
    "deal_stage": "Demo Run",
    "deal_amount": 258,
    "deal_currency_code": "USD",
    "deal_amount_usd": 258,
    "number_of_branches": 2
  },
  {
    "lead_id": "207771155231",
    "lead_link": "https://app.hubspot.com/contacts/9423176/record/0-1/207771155231",
    "createdate": "2026-03-07T23:32:20Z",
    "hs_v2_date_entered_marketingqualifiedlead": "2026-03-07T23:39:00.596Z",
    "hs_v2_date_entered_salesqualifiedlead": "2026-03-11T17:56:07.862Z",
    "hs_v2_date_entered_opportunity": null,
    "firstname": "Ali",
    "lastname": "tortorella",
    "email": "ali@pizzaboyz.co.uk",
    "phone": "+447738595906",
    "jobtitle": null,
    "company": "The pizza boyz",
    "country": "United Kingdom",
    "number_of_locations": 2,
    "lifecyclestage": "salesqualifiedlead",
    "hs_lead_status": "Qualified",
    "hs_analytics_source": "PAID_SOCIAL",
    "hs_analytics_source_data_1": "Facebook",
    "hs_analytics_source_data_2": "supy_facebook_uk_lal_leadgen",
    "new_lead_source": "Marketing",
    "utm_source": null,
    "utm_medium": null,
    "utm_campaign": null,
    "utm_content": null,
    "deal_id": "57856124052",
    "deal_link": "https://app.hubspot.com/contacts/9423176/record/0-3/57856124052",
    "deal_name": "The Pizza Boyz",
    "deal_createdate": "2026-03-11T17:56:07.158Z",
    "deal_stage": "Demo Booked",
    "deal_amount": 200,
    "deal_currency_code": "GBP",
    "deal_amount_usd": null,
    "number_of_branches": 2
  },
  {
    "lead_id": "208146195517",
    "lead_link": "https://app.hubspot.com/contacts/9423176/record/0-1/208146195517",
    "createdate": "2026-03-09T21:18:01Z",
    "hs_v2_date_entered_marketingqualifiedlead": "2026-03-09T21:24:45.782Z",
    "hs_v2_date_entered_salesqualifiedlead": "2026-03-12T06:00:49.462Z",
    "hs_v2_date_entered_opportunity": null,
    "firstname": "Allian Jan",
    "lastname": "Domingo",
    "email": "jan.tastexperts@gmail.com",
    "phone": "+639175274641",
    "jobtitle": null,
    "company": "Global Prime Concepts Inc",
    "country": "Philippines",
    "number_of_locations": 60,
    "lifecyclestage": "salesqualifiedlead",
    "hs_lead_status": "Qualified",
    "hs_analytics_source": "PAID_SOCIAL",
    "hs_analytics_source_data_1": "Facebook",
    "hs_analytics_source_data_2": "supy_facebook_retargetting_tofu_campaign",
    "new_lead_source": "Marketing",
    "utm_source": null,
    "utm_medium": null,
    "utm_campaign": null,
    "utm_content": null,
    "deal_id": "57938975156",
    "deal_link": "https://app.hubspot.com/contacts/9423176/record/0-3/57938975156",
    "deal_name": "Global Prime Concepts Inc",
    "deal_createdate": "2026-03-12T06:00:48.974Z",
    "deal_stage": "Demo Booked",
    "deal_amount": 6000,
    "deal_currency_code": "USD",
    "deal_amount_usd": 6000,
    "number_of_branches": 60
  },
  {
    "lead_id": "207892052632",
    "lead_link": "https://app.hubspot.com/contacts/9423176/record/0-1/207892052632",
    "createdate": "2026-03-08T18:21:09Z",
    "hs_v2_date_entered_marketingqualifiedlead": "2026-03-08T18:28:09.010Z",
    "hs_v2_date_entered_salesqualifiedlead": "2026-03-12T09:37:41.830Z",
    "hs_v2_date_entered_opportunity": "2026-03-27T11:07:00.828Z",
    "firstname": "Luay",
    "lastname": "Torky",
    "email": "luay@saalinvest.com",
    "phone": "+201006073111",
    "jobtitle": "Chief Executive Officer",
    "company": "SAAL Invest",
    "country": "Egypt",
    "number_of_locations": 60,
    "lifecyclestage": "opportunity",
    "hs_lead_status": "Qualified",
    "hs_analytics_source": "PAID_SOCIAL",
    "hs_analytics_source_data_1": "Facebook",
    "hs_analytics_source_data_2": "supy_facebook_retargetting_tofu_campaign",
    "new_lead_source": "Marketing",
    "utm_source": null,
    "utm_medium": null,
    "utm_campaign": null,
    "utm_content": null,
    "deal_id": "57941020933",
    "deal_link": "https://app.hubspot.com/contacts/9423176/record/0-3/57941020933",
    "deal_name": "Saal Invest",
    "deal_createdate": "2026-03-12T09:37:41.152Z",
    "deal_stage": "Demo Run",
    "deal_amount": 6000,
    "deal_currency_code": "USD",
    "deal_amount_usd": 6000,
    "number_of_branches": 60
  },
  {
    "lead_id": "208393310535",
    "lead_link": "https://app.hubspot.com/contacts/9423176/record/0-1/208393310535",
    "createdate": "2026-03-10T19:32:26Z",
    "hs_v2_date_entered_marketingqualifiedlead": "2026-03-10T19:52:27.055Z",
    "hs_v2_date_entered_salesqualifiedlead": "2026-03-12T14:40:13.447Z",
    "hs_v2_date_entered_opportunity": "2026-03-12T14:40:17.601Z",
    "firstname": "Clifford",
    "lastname": "Ng",
    "email": "clifford@ocean.mu",
    "phone": "+2302633103",
    "jobtitle": "Director",
    "company": "Ocean Villas",
    "country": "Mauritius",
    "number_of_locations": 1,
    "lifecyclestage": "opportunity",
    "hs_lead_status": "Qualified",
    "hs_analytics_source": "SOCIAL_MEDIA",
    "hs_analytics_source_data_1": "Facebook",
    "hs_analytics_source_data_2": null,
    "new_lead_source": "Marketing",
    "utm_source": "hs_automation",
    "utm_medium": "email",
    "utm_campaign": null,
    "utm_content": "394471093",
    "deal_id": "57939113035",
    "deal_link": "https://app.hubspot.com/contacts/9423176/record/0-3/57939113035",
    "deal_name": "Ocean Villas- Mauritius",
    "deal_createdate": "2026-03-12T14:40:12.790Z",
    "deal_stage": "Proposal Sent",
    "deal_amount": 160,
    "deal_currency_code": "USD",
    "deal_amount_usd": 160,
    "number_of_branches": 1
  },
  {
    "lead_id": "206638601010",
    "lead_link": "https://app.hubspot.com/contacts/9423176/record/0-1/206638601010",
    "createdate": "2026-03-03T06:52:38Z",
    "hs_v2_date_entered_marketingqualifiedlead": "2026-03-03T06:59:14.851Z",
    "hs_v2_date_entered_salesqualifiedlead": "2026-03-12T23:18:27.232Z",
    "hs_v2_date_entered_opportunity": null,
    "firstname": "George",
    "lastname": "Tang",
    "email": "georgetang1999@outlook.com",
    "phone": "+6582929478",
    "jobtitle": null,
    "company": "Jojis Diner",
    "country": "Singapore",
    "number_of_locations": 3,
    "lifecyclestage": "salesqualifiedlead",
    "hs_lead_status": "Qualified",
    "hs_analytics_source": "PAID_SOCIAL",
    "hs_analytics_source_data_1": "Facebook",
    "hs_analytics_source_data_2": "supy_facebook_singapore_meta",
    "new_lead_source": "Marketing",
    "utm_source": null,
    "utm_medium": null,
    "utm_campaign": null,
    "utm_content": null,
    "deal_id": "57941049165",
    "deal_link": "https://app.hubspot.com/contacts/9423176/record/0-3/57941049165",
    "deal_name": "Joji Diner",
    "deal_createdate": "2026-03-12T23:18:26.613Z",
    "deal_stage": "Closed/Lost",
    "deal_amount": 537,
    "deal_currency_code": "USD",
    "deal_amount_usd": 537,
    "number_of_branches": 3
  },
  {
    "lead_id": "207276649850",
    "lead_link": "https://app.hubspot.com/contacts/9423176/record/0-1/207276649850",
    "createdate": "2026-03-05T16:42:25Z",
    "hs_v2_date_entered_marketingqualifiedlead": "2026-03-05T16:49:05.125Z",
    "hs_v2_date_entered_salesqualifiedlead": "2026-03-12T23:44:25.241Z",
    "hs_v2_date_entered_opportunity": null,
    "firstname": "Eleck",
    "lastname": "Diestro",
    "email": "eleckuisine@gmail.com",
    "phone": "+639063686944",
    "jobtitle": null,
    "company": "Eleckuisine",
    "country": "Philippines",
    "number_of_locations": 3,
    "lifecyclestage": "salesqualifiedlead",
    "hs_lead_status": "Qualified",
    "hs_analytics_source": "PAID_SOCIAL",
    "hs_analytics_source_data_1": "Facebook",
    "hs_analytics_source_data_2": "supy_facebook_philippines_meta",
    "new_lead_source": "Marketing",
    "utm_source": null,
    "utm_medium": null,
    "utm_campaign": null,
    "utm_content": null,
    "deal_id": "57939136174",
    "deal_link": "https://app.hubspot.com/contacts/9423176/record/0-3/57939136174",
    "deal_name": "Eleckuisine",
    "deal_createdate": "2026-03-12T23:44:24.498Z",
    "deal_stage": "Demo Booked",
    "deal_amount": 297,
    "deal_currency_code": "USD",
    "deal_amount_usd": 297,
    "number_of_branches": 3
  },
  {
    "lead_id": "208200979008",
    "lead_link": "https://app.hubspot.com/contacts/9423176/record/0-1/208200979008",
    "createdate": "2026-03-10T02:00:38Z",
    "hs_v2_date_entered_marketingqualifiedlead": "2026-03-10T02:07:42.985Z",
    "hs_v2_date_entered_salesqualifiedlead": "2026-03-13T10:05:34.983Z",
    "hs_v2_date_entered_opportunity": "2026-03-13T10:05:38.476Z",
    "firstname": "Kurt",
    "lastname": "Wohlenberg",
    "email": "kurtwohlenberg@gmail.com",
    "phone": "+27726001126",
    "jobtitle": null,
    "company": "Hyatt",
    "country": "South Africa",
    "number_of_locations": 10,
    "lifecyclestage": "opportunity",
    "hs_lead_status": "Qualified",
    "hs_analytics_source": "PAID_SOCIAL",
    "hs_analytics_source_data_1": "Facebook",
    "hs_analytics_source_data_2": "supy_facebook_south_africa_meta",
    "new_lead_source": "Marketing",
    "utm_source": null,
    "utm_medium": null,
    "utm_campaign": null,
    "utm_content": null,
    "deal_id": "57938955638",
    "deal_link": "https://app.hubspot.com/contacts/9423176/record/0-3/57938955638",
    "deal_name": "Hyatt Hotel",
    "deal_createdate": "2026-03-13T10:05:32.311Z",
    "deal_stage": "Closed/Lost",
    "deal_amount": 530,
    "deal_currency_code": "USD",
    "deal_amount_usd": 530,
    "number_of_branches": 10
  },
  {
    "lead_id": "208028957205",
    "lead_link": "https://app.hubspot.com/contacts/9423176/record/0-1/208028957205",
    "createdate": "2026-03-09T10:52:39Z",
    "hs_v2_date_entered_marketingqualifiedlead": "2026-03-09T10:59:16.536Z",
    "hs_v2_date_entered_salesqualifiedlead": "2026-03-17T04:04:50.073Z",
    "hs_v2_date_entered_opportunity": "2026-03-17T04:05:09.970Z",
    "firstname": "Deesamer",
    "lastname": "Yimprasit",
    "email": "deesamer@pocketrocket.pro",
    "phone": "+66970405000",
    "jobtitle": null,
    "company": "PRC",
    "country": "Thailand",
    "number_of_locations": 6,
    "lifecyclestage": "customer",
    "hs_lead_status": "Customer",
    "hs_analytics_source": "PAID_SOCIAL",
    "hs_analytics_source_data_1": "Facebook",
    "hs_analytics_source_data_2": "supy_facebook_thailand_meta",
    "new_lead_source": "Marketing",
    "utm_source": null,
    "utm_medium": null,
    "utm_campaign": null,
    "utm_content": null,
    "deal_id": "58025414982",
    "deal_link": "https://app.hubspot.com/contacts/9423176/record/0-3/58025414982",
    "deal_name": "Pocket Rocket",
    "deal_createdate": "2026-03-17T04:04:49.334Z",
    "deal_stage": "Closed/Won",
    "deal_amount": 238,
    "deal_currency_code": "USD",
    "deal_amount_usd": 238,
    "number_of_branches": 6
  },
  {
    "lead_id": "209558631536",
    "lead_link": "https://app.hubspot.com/contacts/9423176/record/0-1/209558631536",
    "createdate": "2026-03-16T15:00:15Z",
    "hs_v2_date_entered_marketingqualifiedlead": "2026-03-16T15:07:12.981Z",
    "hs_v2_date_entered_salesqualifiedlead": "2026-03-17T06:30:15.530Z",
    "hs_v2_date_entered_opportunity": "2026-03-18T23:17:09.018Z",
    "firstname": "Mark",
    "lastname": "Cua",
    "email": "markdavidson.cua@gmail.com",
    "phone": "+639178672557",
    "jobtitle": "Owner",
    "company": "globalink",
    "country": "Philippines",
    "number_of_locations": 2,
    "lifecyclestage": "opportunity",
    "hs_lead_status": "Qualified",
    "hs_analytics_source": "PAID_SOCIAL",
    "hs_analytics_source_data_1": "Facebook",
    "hs_analytics_source_data_2": "supy_facebook_philippines_meta",
    "new_lead_source": "Marketing",
    "utm_source": null,
    "utm_medium": null,
    "utm_campaign": null,
    "utm_content": null,
    "deal_id": "58025047835",
    "deal_link": "https://app.hubspot.com/contacts/9423176/record/0-3/58025047835",
    "deal_name": "Globalink",
    "deal_createdate": "2026-03-17T06:30:10.512Z",
    "deal_stage": "Under Negotiation",
    "deal_amount": 207.1,
    "deal_currency_code": "USD",
    "deal_amount_usd": 207.1,
    "number_of_branches": 2
  },
  {
    "lead_id": "207793942949",
    "lead_link": "https://app.hubspot.com/contacts/9423176/record/0-1/207793942949",
    "createdate": "2026-03-08T03:29:30Z",
    "hs_v2_date_entered_marketingqualifiedlead": "2026-03-08T03:36:15.388Z",
    "hs_v2_date_entered_salesqualifiedlead": "2026-03-17T22:34:57.502Z",
    "hs_v2_date_entered_opportunity": "2026-03-18T06:46:02.049Z",
    "firstname": "Leyla",
    "lastname": "Mayko",
    "email": "info@sassysamui.com",
    "phone": "+66613548861",
    "jobtitle": "MG",
    "company": "Sassy",
    "country": "Thailand",
    "number_of_locations": 2,
    "lifecyclestage": "customer",
    "hs_lead_status": "Customer",
    "hs_analytics_source": "PAID_SOCIAL",
    "hs_analytics_source_data_1": "Facebook",
    "hs_analytics_source_data_2": "supy_facebook_thailand_meta",
    "new_lead_source": "Marketing",
    "utm_source": null,
    "utm_medium": null,
    "utm_campaign": null,
    "utm_content": null,
    "deal_id": "58098490388",
    "deal_link": "https://app.hubspot.com/contacts/9423176/record/0-3/58098490388",
    "deal_name": "Sassy",
    "deal_createdate": "2026-03-17T22:34:56.661Z",
    "deal_stage": "Closed/Won",
    "deal_amount": 258,
    "deal_currency_code": "USD",
    "deal_amount_usd": 258,
    "number_of_branches": 2
  },
  {
    "lead_id": "208065943142",
    "lead_link": "https://app.hubspot.com/contacts/9423176/record/0-1/208065943142",
    "createdate": "2026-03-09T14:29:26Z",
    "hs_v2_date_entered_marketingqualifiedlead": "2026-03-09T14:37:31.599Z",
    "hs_v2_date_entered_salesqualifiedlead": "2026-03-18T04:59:09.979Z",
    "hs_v2_date_entered_opportunity": "2026-03-20T05:56:33.356Z",
    "firstname": "Ian",
    "lastname": "IK",
    "email": "chongen13@gmail.com",
    "phone": "+6588205622",
    "jobtitle": "25",
    "company": "Basil King",
    "country": "Singapore",
    "number_of_locations": 10,
    "lifecyclestage": "opportunity",
    "hs_lead_status": "Qualified",
    "hs_analytics_source": "PAID_SOCIAL",
    "hs_analytics_source_data_1": "Facebook",
    "hs_analytics_source_data_2": "supy_facebook_singapore_meta",
    "new_lead_source": "Marketing",
    "utm_source": null,
    "utm_medium": null,
    "utm_campaign": null,
    "utm_content": null,
    "deal_id": "58025513223",
    "deal_link": "https://app.hubspot.com/contacts/9423176/record/0-3/58025513223",
    "deal_name": "Basil King",
    "deal_createdate": "2026-03-18T04:59:09.450Z",
    "deal_stage": "Closed/Lost",
    "deal_amount": 2674,
    "deal_currency_code": "USD",
    "deal_amount_usd": 2674,
    "number_of_branches": 10
  },
  {
    "lead_id": "210389001023",
    "lead_link": "https://app.hubspot.com/contacts/9423176/record/0-1/210389001023",
    "createdate": "2026-03-19T19:11:10Z",
    "hs_v2_date_entered_marketingqualifiedlead": "2026-03-19T19:17:53.608Z",
    "hs_v2_date_entered_salesqualifiedlead": null,
    "hs_v2_date_entered_opportunity": "2026-03-23T10:42:02.184Z",
    "firstname": "Sajeev De",
    "lastname": "Silva",
    "email": "coffee@drinkdivide.com",
    "phone": "+94773660666",
    "jobtitle": null,
    "company": "Divide",
    "country": "Sri Lanka",
    "number_of_locations": 2,
    "lifecyclestage": "opportunity",
    "hs_lead_status": "Qualified",
    "hs_analytics_source": "PAID_SOCIAL",
    "hs_analytics_source_data_1": "Facebook",
    "hs_analytics_source_data_2": "supy_facebook_sri_lanka_meta",
    "new_lead_source": "Marketing",
    "utm_source": null,
    "utm_medium": null,
    "utm_campaign": null,
    "utm_content": null,
    "deal_id": "58208780300",
    "deal_link": "https://app.hubspot.com/contacts/9423176/record/0-3/58208780300",
    "deal_name": "Tea Avenue- Sri Lanka",
    "deal_createdate": "2026-03-23T10:41:57.368Z",
    "deal_stage": "Proposal Sent",
    "deal_amount": 990,
    "deal_currency_code": "USD",
    "deal_amount_usd": 990,
    "number_of_branches": 2
  },
  {
    "lead_id": "207781649513",
    "lead_link": "https://app.hubspot.com/contacts/9423176/record/0-1/207781649513",
    "createdate": "2026-03-08T00:53:34Z",
    "hs_v2_date_entered_marketingqualifiedlead": "2026-03-08T01:00:09.897Z",
    "hs_v2_date_entered_salesqualifiedlead": "2026-03-19T05:42:17.370Z",
    "hs_v2_date_entered_opportunity": "2026-03-19T05:42:20.680Z",
    "firstname": "Alfonso",
    "lastname": "Pedrosa",
    "email": "alfonsogpedrosa@gmail.com",
    "phone": "+639178823667",
    "jobtitle": null,
    "company": "CLR Concepts",
    "country": "Philippines",
    "number_of_locations": 2,
    "lifecyclestage": "opportunity",
    "hs_lead_status": "Qualified",
    "hs_analytics_source": "PAID_SOCIAL",
    "hs_analytics_source_data_1": "Facebook",
    "hs_analytics_source_data_2": "supy_facebook_philippines_meta",
    "new_lead_source": "Marketing",
    "utm_source": null,
    "utm_medium": null,
    "utm_campaign": null,
    "utm_content": null,
    "deal_id": "58134841484",
    "deal_link": "https://app.hubspot.com/contacts/9423176/record/0-3/58134841484",
    "deal_name": "CLR Concepts",
    "deal_createdate": "2026-03-19T05:42:16.777Z",
    "deal_stage": "Under Negotiation",
    "deal_amount": 258,
    "deal_currency_code": "USD",
    "deal_amount_usd": 258,
    "number_of_branches": 2
  },
  {
    "lead_id": "210157656927",
    "lead_link": "https://app.hubspot.com/contacts/9423176/record/0-1/210157656927",
    "createdate": "2026-03-18T17:20:49Z",
    "hs_v2_date_entered_marketingqualifiedlead": "2026-03-18T17:27:52.437Z",
    "hs_v2_date_entered_salesqualifiedlead": "2026-03-19T06:17:03.671Z",
    "hs_v2_date_entered_opportunity": "2026-03-26T05:28:03.135Z",
    "firstname": "Ruba",
    "lastname": "Nada",
    "email": "ruba@nada.com.my",
    "phone": "+60122995588",
    "jobtitle": null,
    "company": "NCB",
    "country": "Malaysia",
    "number_of_locations": 10,
    "lifecyclestage": "opportunity",
    "hs_lead_status": "Qualified",
    "hs_analytics_source": "PAID_SOCIAL",
    "hs_analytics_source_data_1": "Facebook",
    "hs_analytics_source_data_2": "supy_facebook_hk_my_lal_leadgen",
    "new_lead_source": "Marketing",
    "utm_source": null,
    "utm_medium": null,
    "utm_campaign": null,
    "utm_content": null,
    "deal_id": "58134904665",
    "deal_link": "https://app.hubspot.com/contacts/9423176/record/0-3/58134904665",
    "deal_name": "Nada Capital",
    "deal_createdate": "2026-03-19T06:17:02.922Z",
    "deal_stage": "Proposal Sent",
    "deal_amount": 1090,
    "deal_currency_code": "USD",
    "deal_amount_usd": 1090,
    "number_of_branches": 10
  },
  {
    "lead_id": "207800229472",
    "lead_link": "https://app.hubspot.com/contacts/9423176/record/0-1/207800229472",
    "createdate": "2026-03-08T05:25:03Z",
    "hs_v2_date_entered_marketingqualifiedlead": "2026-03-08T05:31:54.481Z",
    "hs_v2_date_entered_salesqualifiedlead": "2026-03-24T19:02:39.051Z",
    "hs_v2_date_entered_opportunity": "2026-03-24T19:03:45.802Z",
    "firstname": "Sarmad",
    "lastname": "Hama",
    "email": "sarmad@hamagroup.co",
    "phone": "+9647701525140",
    "jobtitle": null,
    "company": "7",
    "country": "Iraq",
    "number_of_locations": 2,
    "lifecyclestage": "opportunity",
    "hs_lead_status": "Qualified",
    "hs_analytics_source": "PAID_SOCIAL",
    "hs_analytics_source_data_1": "Facebook",
    "hs_analytics_source_data_2": "supy_facebook_retargetting_tofu_campaign",
    "new_lead_source": "Marketing",
    "utm_source": null,
    "utm_medium": null,
    "utm_campaign": null,
    "utm_content": null,
    "deal_id": "58289370406",
    "deal_link": "https://app.hubspot.com/contacts/9423176/record/0-3/58289370406",
    "deal_name": "Hama Group",
    "deal_createdate": "2026-03-24T19:02:38.164Z",
    "deal_stage": "Closed/Lost",
    "deal_amount": 200,
    "deal_currency_code": "USD",
    "deal_amount_usd": 200,
    "number_of_branches": 2
  },
  {
    "lead_id": "205003500572",
    "lead_link": "https://app.hubspot.com/contacts/9423176/record/0-1/205003500572",
    "createdate": "2026-02-24T11:10:49Z",
    "hs_v2_date_entered_marketingqualifiedlead": "2026-02-24T11:17:26.981Z",
    "hs_v2_date_entered_salesqualifiedlead": null,
    "hs_v2_date_entered_opportunity": "2026-03-24T05:22:57.294Z",
    "firstname": "Ria",
    "lastname": "Alcover",
    "email": "stktabay@gmail.com",
    "phone": "+639173280927",
    "jobtitle": null,
    "company": "STK ta Bai sa Paolito's Seafood House",
    "country": "Philippines",
    "number_of_locations": 2,
    "lifecyclestage": "customer",
    "hs_lead_status": "Customer",
    "hs_analytics_source": "PAID_SOCIAL",
    "hs_analytics_source_data_1": "Facebook",
    "hs_analytics_source_data_2": "supy_facebook_philippines_meta",
    "new_lead_source": "Marketing",
    "utm_source": null,
    "utm_medium": null,
    "utm_campaign": null,
    "utm_content": null,
    "deal_id": "58254501766",
    "deal_link": "https://app.hubspot.com/contacts/9423176/record/0-3/58254501766",
    "deal_name": "STK ta Bai Paolito's Seafood House Inc",
    "deal_createdate": "2026-03-24T05:22:52.723Z",
    "deal_stage": "Closed/Won",
    "deal_amount": 238,
    "deal_currency_code": "USD",
    "deal_amount_usd": 238,
    "number_of_branches": 2
  },
  {
    "lead_id": "124664440655",
    "lead_link": "https://app.hubspot.com/contacts/9423176/record/0-1/124664440655",
    "createdate": "2025-05-25T14:26:38Z",
    "hs_v2_date_entered_marketingqualifiedlead": "2025-05-25T14:27:00.866Z",
    "hs_v2_date_entered_salesqualifiedlead": "2026-03-26T11:47:46.090Z",
    "hs_v2_date_entered_opportunity": null,
    "firstname": "Reynaldo",
    "lastname": "Sayo Jr",
    "email": "reynaldojr.sayo@yahoo.com.ph",
    "phone": "+966553294426",
    "jobtitle": "operations_manager",
    "company": "Klatch",
    "country": "Saudi Arabia",
    "number_of_locations": 2,
    "lifecyclestage": "salesqualifiedlead",
    "hs_lead_status": "Unresponsive",
    "hs_analytics_source": "PAID_SOCIAL",
    "hs_analytics_source_data_1": "Facebook",
    "hs_analytics_source_data_2": "supy_facebook_gcc_lal_leadgen",
    "new_lead_source": "Marketing",
    "utm_source": null,
    "utm_medium": null,
    "utm_campaign": null,
    "utm_content": null,
    "deal_id": "58332296843",
    "deal_link": "https://app.hubspot.com/contacts/9423176/record/0-3/58332296843",
    "deal_name": "Klatch Coffee",
    "deal_createdate": "2026-03-26T11:47:40.347Z",
    "deal_stage": "Closed/Lost",
    "deal_amount": 199,
    "deal_currency_code": "USD",
    "deal_amount_usd": 199,
    "number_of_branches": 2
  },
  {
    "lead_id": "118837405030",
    "lead_link": "https://app.hubspot.com/contacts/9423176/record/0-1/118837405030",
    "createdate": "2025-05-03T01:26:57Z",
    "hs_v2_date_entered_marketingqualifiedlead": "2025-05-03T01:27:22.864Z",
    "hs_v2_date_entered_salesqualifiedlead": "2026-03-27T07:18:37.829Z",
    "hs_v2_date_entered_opportunity": null,
    "firstname": "Subin",
    "lastname": "C Devasia",
    "email": "subin498@gmail.com",
    "phone": "+966567437988",
    "jobtitle": "operations_manager",
    "company": "memories",
    "country": "Saudi Arabia",
    "number_of_locations": 1,
    "lifecyclestage": "salesqualifiedlead",
    "hs_lead_status": "Qualified",
    "hs_analytics_source": "PAID_SOCIAL",
    "hs_analytics_source_data_1": "Facebook",
    "hs_analytics_source_data_2": "supy_facebook_gcc_lal_leadgen",
    "new_lead_source": "Marketing",
    "utm_source": null,
    "utm_medium": null,
    "utm_campaign": null,
    "utm_content": null,
    "deal_id": "58404193333",
    "deal_link": "https://app.hubspot.com/contacts/9423176/record/0-3/58404193333",
    "deal_name": "Memories",
    "deal_createdate": "2026-03-27T07:18:34.741Z",
    "deal_stage": "Demo Booked",
    "deal_amount": 199,
    "deal_currency_code": "USD",
    "deal_amount_usd": 199,
    "number_of_branches": 1
  },
  {
    "lead_id": "206635501082",
    "lead_link": "https://app.hubspot.com/contacts/9423176/record/0-1/206635501082",
    "createdate": "2026-03-03T05:40:37Z",
    "hs_v2_date_entered_marketingqualifiedlead": "2026-03-03T05:47:12.701Z",
    "hs_v2_date_entered_salesqualifiedlead": "2026-03-27T10:52:23.923Z",
    "hs_v2_date_entered_opportunity": null,
    "firstname": "Rob",
    "lastname": "Howse",
    "email": "officehowse@gmail.com",
    "phone": "+27835832389",
    "jobtitle": null,
    "company": "Mugg & Bean",
    "country": "South Africa",
    "number_of_locations": 2,
    "lifecyclestage": "salesqualifiedlead",
    "hs_lead_status": "Qualified",
    "hs_analytics_source": "PAID_SOCIAL",
    "hs_analytics_source_data_1": "Facebook",
    "hs_analytics_source_data_2": "supy_facebook_south_africa_meta",
    "new_lead_source": "Marketing",
    "utm_source": null,
    "utm_medium": null,
    "utm_campaign": null,
    "utm_content": null,
    "deal_id": "58404196663",
    "deal_link": "https://app.hubspot.com/contacts/9423176/record/0-3/58404196663",
    "deal_name": "Mugg & Bean",
    "deal_createdate": "2026-03-27T10:52:22.551Z",
    "deal_stage": "Closed/Lost",
    "deal_amount": 199,
    "deal_currency_code": "USD",
    "deal_amount_usd": 199,
    "number_of_branches": 2
  },
  {
    "lead_id": "211995058438",
    "lead_link": "https://app.hubspot.com/contacts/9423176/record/0-1/211995058438",
    "createdate": "2026-03-27T12:15:17Z",
    "hs_v2_date_entered_marketingqualifiedlead": "2026-03-27T12:21:57.242Z",
    "hs_v2_date_entered_salesqualifiedlead": "2026-03-27T13:45:38.788Z",
    "hs_v2_date_entered_opportunity": "2026-04-06T06:20:04.132Z",
    "firstname": "Béatrice",
    "lastname": "Santenoise",
    "email": "thecosy@gmail.com",
    "phone": "+66809238340",
    "jobtitle": null,
    "company": "The Cosy Beach Resort -Pool,Bar and Restaurant",
    "country": "Thailand",
    "number_of_locations": 2,
    "lifecyclestage": "opportunity",
    "hs_lead_status": "Qualified",
    "hs_analytics_source": "PAID_SOCIAL",
    "hs_analytics_source_data_1": "Facebook",
    "hs_analytics_source_data_2": "supy_facebook_thailand_meta",
    "new_lead_source": "Marketing",
    "utm_source": null,
    "utm_medium": null,
    "utm_campaign": null,
    "utm_content": null,
    "deal_id": "58404201482",
    "deal_link": "https://app.hubspot.com/contacts/9423176/record/0-3/58404201482",
    "deal_name": "The Cosy Beach Resort & Spa- Thailand",
    "deal_createdate": "2026-03-27T13:45:31.510Z",
    "deal_stage": "Demo Run",
    "deal_amount": 200,
    "deal_currency_code": "USD",
    "deal_amount_usd": 200,
    "number_of_branches": 2
  },
  {
    "lead_id": "212273152348",
    "lead_link": "https://app.hubspot.com/contacts/9423176/record/0-1/212273152348",
    "createdate": "2026-03-29T03:06:18Z",
    "hs_v2_date_entered_marketingqualifiedlead": "2026-03-29T03:13:06.343Z",
    "hs_v2_date_entered_salesqualifiedlead": "2026-03-30T03:46:01.039Z",
    "hs_v2_date_entered_opportunity": null,
    "firstname": "Jeffrey",
    "lastname": "Wu",
    "email": "jeffriwu@gmail.com",
    "phone": "+886928809435",
    "jobtitle": null,
    "company": "One Kara",
    "country": "Taiwan",
    "number_of_locations": 4,
    "lifecyclestage": "salesqualifiedlead",
    "hs_lead_status": "Qualified",
    "hs_analytics_source": "PAID_SOCIAL",
    "hs_analytics_source_data_1": "Facebook",
    "hs_analytics_source_data_2": "supy_facebook_taiwan_meta",
    "new_lead_source": "Marketing",
    "utm_source": null,
    "utm_medium": null,
    "utm_campaign": null,
    "utm_content": null,
    "deal_id": "58479497289",
    "deal_link": "https://app.hubspot.com/contacts/9423176/record/0-3/58479497289",
    "deal_name": "One Kara",
    "deal_createdate": "2026-03-30T03:45:56.223Z",
    "deal_stage": "Demo Booked",
    "deal_amount": 745,
    "deal_currency_code": "USD",
    "deal_amount_usd": 745,
    "number_of_branches": 4
  },
  {
    "lead_id": "212033079901",
    "lead_link": "https://app.hubspot.com/contacts/9423176/record/0-1/212033079901",
    "createdate": "2026-03-29T02:13:26Z",
    "hs_v2_date_entered_marketingqualifiedlead": "2026-03-29T02:20:37.950Z",
    "hs_v2_date_entered_salesqualifiedlead": null,
    "hs_v2_date_entered_opportunity": "2026-03-30T00:01:23.028Z",
    "firstname": "Faith",
    "lastname": "Castillo",
    "email": "castillo.faith27@gmail.com",
    "phone": "+639054427166",
    "jobtitle": null,
    "company": "SUPERSAM",
    "country": "Philippines",
    "number_of_locations": 5,
    "lifecyclestage": "opportunity",
    "hs_lead_status": "Trying to reach",
    "hs_analytics_source": "PAID_SOCIAL",
    "hs_analytics_source_data_1": "Facebook",
    "hs_analytics_source_data_2": "supy_facebook_philippines_meta",
    "new_lead_source": "Marketing",
    "utm_source": "meta",
    "utm_medium": "ads",
    "utm_campaign": "Philippines",
    "utm_content": null,
    "deal_id": "58479616544",
    "deal_link": "https://app.hubspot.com/contacts/9423176/record/0-3/58479616544",
    "deal_name": "SuperSam",
    "deal_createdate": "2026-03-30T00:01:18.490Z",
    "deal_stage": "Proposal Sent",
    "deal_amount": 545,
    "deal_currency_code": "USD",
    "deal_amount_usd": 545,
    "number_of_branches": 5
  },
  {
    "lead_id": "204535101876",
    "lead_link": "https://app.hubspot.com/contacts/9423176/record/0-1/204535101876",
    "createdate": "2026-02-22T14:06:08Z",
    "hs_v2_date_entered_marketingqualifiedlead": "2026-02-22T14:12:41.329Z",
    "hs_v2_date_entered_salesqualifiedlead": null,
    "hs_v2_date_entered_opportunity": "2026-03-29T23:11:45.170Z",
    "firstname": "Corinne",
    "lastname": "Castaneda",
    "email": "cmycastaneda@yahoo.com",
    "phone": "+639175215870",
    "jobtitle": "Owner",
    "company": "WANGUS Corp",
    "country": "Philippines",
    "number_of_locations": 4,
    "lifecyclestage": "opportunity",
    "hs_lead_status": "Qualified",
    "hs_analytics_source": "PAID_SOCIAL",
    "hs_analytics_source_data_1": "Facebook",
    "hs_analytics_source_data_2": "supy_facebook_philippines_meta",
    "new_lead_source": "Marketing",
    "utm_source": null,
    "utm_medium": null,
    "utm_campaign": null,
    "utm_content": null,
    "deal_id": "58474808983",
    "deal_link": "https://app.hubspot.com/contacts/9423176/record/0-3/58474808983",
    "deal_name": "WANGUS Corp",
    "deal_createdate": "2026-03-29T23:11:41.005Z",
    "deal_stage": "Demo Run",
    "deal_amount": 436,
    "deal_currency_code": "USD",
    "deal_amount_usd": 436,
    "number_of_branches": 4
  },
  {
    "lead_id": "212659055712",
    "lead_link": "https://app.hubspot.com/contacts/9423176/record/0-1/212659055712",
    "createdate": "2026-03-31T02:32:16Z",
    "hs_v2_date_entered_marketingqualifiedlead": "2026-03-31T02:38:57.460Z",
    "hs_v2_date_entered_salesqualifiedlead": "2026-03-31T03:09:09.690Z",
    "hs_v2_date_entered_opportunity": null,
    "firstname": "Coral",
    "lastname": "Chau",
    "email": "coral@elite-target.com",
    "phone": "+85296635469",
    "jobtitle": "Owner",
    "company": "Elite Target Limited",
    "country": "Hong Kong",
    "number_of_locations": 1,
    "lifecyclestage": "salesqualifiedlead",
    "hs_lead_status": "Qualified",
    "hs_analytics_source": "PAID_SOCIAL",
    "hs_analytics_source_data_1": "Facebook",
    "hs_analytics_source_data_2": "supy_facebook_hk_my_lal_leadgen",
    "new_lead_source": "Marketing",
    "utm_source": null,
    "utm_medium": null,
    "utm_campaign": null,
    "utm_content": null,
    "deal_id": "58567561628",
    "deal_link": "https://app.hubspot.com/contacts/9423176/record/0-3/58567561628",
    "deal_name": "Elite Target Limited",
    "deal_createdate": "2026-03-31T03:09:06.486Z",
    "deal_stage": "Closed/Lost",
    "deal_amount": 199,
    "deal_currency_code": "USD",
    "deal_amount_usd": 199,
    "number_of_branches": 1
  },
  {
    "lead_id": "212244492934",
    "lead_link": "https://app.hubspot.com/contacts/9423176/record/0-1/212244492934",
    "createdate": "2026-03-28T21:39:33Z",
    "hs_v2_date_entered_marketingqualifiedlead": "2026-03-28T21:39:50.829Z",
    "hs_v2_date_entered_salesqualifiedlead": "2026-03-31T06:34:15.349Z",
    "hs_v2_date_entered_opportunity": null,
    "firstname": "Odira",
    "lastname": "Okwuagwu",
    "email": "rubel.okwuagwu@rubelsandangels.com",
    "phone": "+2348120536702",
    "jobtitle": null,
    "company": "Rubels&Angels",
    "country": "Nigeria",
    "number_of_locations": 4,
    "lifecyclestage": "salesqualifiedlead",
    "hs_lead_status": "Following up",
    "hs_analytics_source": "PAID_SOCIAL",
    "hs_analytics_source_data_1": "Facebook",
    "hs_analytics_source_data_2": "supy_facebook_nigeria_meta",
    "new_lead_source": "Marketing",
    "utm_source": null,
    "utm_medium": null,
    "utm_campaign": null,
    "utm_content": null,
    "deal_id": null,
    "deal_link": null,
    "deal_name": null,
    "deal_createdate": null,
    "deal_stage": null,
    "deal_amount": null,
    "deal_currency_code": null,
    "deal_amount_usd": null,
    "number_of_branches": 4
  },
  {
    "lead_id": "212292025488",
    "lead_link": "https://app.hubspot.com/contacts/9423176/record/0-1/212292025488",
    "createdate": "2026-03-29T07:46:01Z",
    "hs_v2_date_entered_marketingqualifiedlead": "2026-03-29T07:52:40.310Z",
    "hs_v2_date_entered_salesqualifiedlead": "2026-03-31T11:37:44.913Z",
    "hs_v2_date_entered_opportunity": null,
    "firstname": "Chatree",
    "lastname": "Chevawattana",
    "email": "andy.chevawattana@gmail.com",
    "phone": "+66828280194",
    "jobtitle": null,
    "company": "cherchim",
    "country": "Thailand",
    "number_of_locations": 2,
    "lifecyclestage": "salesqualifiedlead",
    "hs_lead_status": "Qualified",
    "hs_analytics_source": "PAID_SOCIAL",
    "hs_analytics_source_data_1": "Facebook",
    "hs_analytics_source_data_2": "supy_facebook_thailand_meta",
    "new_lead_source": "Marketing",
    "utm_source": null,
    "utm_medium": null,
    "utm_campaign": null,
    "utm_content": null,
    "deal_id": "58567568825",
    "deal_link": "https://app.hubspot.com/contacts/9423176/record/0-3/58567568825",
    "deal_name": "Cherchim Thailand",
    "deal_createdate": "2026-03-31T11:37:44.145Z",
    "deal_stage": "Demo Booked",
    "deal_amount": 199,
    "deal_currency_code": "USD",
    "deal_amount_usd": 199,
    "number_of_branches": 2
  }
]
