[
  {
    "date": "2026-02-22",
    "campaign_id": "120207533114190775",
    "campaign_name": "Supy_Facebook_AUS_LAL_Leadgen",
    "adset_id": "120211091446780775",
    "adset_name": "LAL_Admin_AUS_Facebook_Lead",
    "ad_id": "120211091446770775",
    "ad_name": "LAL_Admin_AUS_Facebook_Lead_Ad",
    "country": "AU",
    "impressions": 2454,
    "clicks": 26,
    "reach": 2135,
    "leads": 1,
    "spend": 80.3,
    "level": "ad"
  },
  {
    "date": "2026-02-22",
    "campaign_id": "120207533114190775",
    "campaign_name": "Supy_Facebook_AUS_LAL_Leadgen",
    "adset_id": "120219950339920775",
    "adset_name": "LAL_Admin_NZ_Facebook_Lead",
    "ad_id": "120219950339930775",
    "ad_name": "LAL_Admin_NZ_Facebook_Lead_Ad",
    "country": "NZ",
    "impressions": 2195,
    "clicks": 20,
    "reach": 1360,
    "leads": 0,
    "spend": 45.45,
    "level": "ad"
  },
  {
    "date": "2026-02-22",
    "campaign_id": "120227305650640775",
    "campaign_name": "Supy_Facebook_HK_MY_LAL_Leadgen",
    "adset_id": "120227305650710775",
    "adset_name": "LAL_Admin_HK_MY_Facebook_Leadgen",
    "ad_id": "120227305650700775",
    "ad_name": "LAL_Admin_HK_MY _Facebook_Lead_Ad",
    "country": "MY",
    "impressions": 3190,
    "clicks": 40,
    "reach": 2045,
    "leads": 1,
    "spend": 31.13,
    "level": "ad"
  },
  {
    "date": "2026-02-22",
    "campaign_id": "120227305650640775",
    "campaign_name": "Supy_Facebook_HK_MY_LAL_Leadgen",
    "adset_id": "120234967340970775",
    "adset_name": "LAL_Admin_HK_Facebook_Leadgen_Launch",
    "ad_id": "120234967340980775",
    "ad_name": "LAL_Admin_HK _Facebook_Lead_Ad",
    "country": "HK",
    "impressions": 1713,
    "clicks": 14,
    "reach": 1023,
    "leads": 0,
    "spend": 27.53,
    "level": "ad"
  },
  {
    "date": "2026-02-22",
    "campaign_id": "120236084000340775",
    "campaign_name": "Supy_Facebook_Global_Retargetting_campaign",
    "adset_id": "120236084000350775",
    "adset_name": "Supy_Facebook_Form_openers_and_website_visitors",
    "ad_id": "120236084000330775",
    "ad_name": "Custom_ audience_Ad_v1",
    "country": "AU",
    "impressions": 63,
    "clicks": 0,
    "reach": 34,
    "leads": 0,
    "spend": 0.77,
    "level": "ad"
  },
  {
    "date": "2026-02-22",
    "campaign_id": "120236084000340775",
    "campaign_name": "Supy_Facebook_Global_Retargetting_campaign",
    "adset_id": "120236084000350775",
    "adset_name": "Supy_Facebook_Form_openers_and_website_visitors",
    "ad_id": "120236084000330775",
    "ad_name": "Custom_ audience_Ad_v1",
    "country": "BH",
    "impressions": 413,
    "clicks": 4,
    "reach": 270,
    "leads": 0,
    "spend": 0.92,
    "level": "ad"
  },
  {
    "date": "2026-02-22",
    "campaign_id": "120236084000340775",
    "campaign_name": "Supy_Facebook_Global_Retargetting_campaign",
    "adset_id": "120236084000350775",
    "adset_name": "Supy_Facebook_Form_openers_and_website_visitors",
    "ad_id": "120236084000330775",
    "ad_name": "Custom_ audience_Ad_v1",
    "country": "HK",
    "impressions": 40,
    "clicks": 0,
    "reach": 35,
    "leads": 0,
    "spend": 0.31,
    "level": "ad"
  },
  {
    "date": "2026-02-22",
    "campaign_id": "120236084000340775",
    "campaign_name": "Supy_Facebook_Global_Retargetting_campaign",
    "adset_id": "120236084000350775",
    "adset_name": "Supy_Facebook_Form_openers_and_website_visitors",
    "ad_id": "120236084000330775",
    "ad_name": "Custom_ audience_Ad_v1",
    "country": "MY",
    "impressions": 11897,
    "clicks": 103,
    "reach": 6934,
    "leads": 0,
    "spend": 22.18,
    "level": "ad"
  },
  {
    "date": "2026-02-22",
    "campaign_id": "120236084000340775",
    "campaign_name": "Supy_Facebook_Global_Retargetting_campaign",
    "adset_id": "120236084000350775",
    "adset_name": "Supy_Facebook_Form_openers_and_website_visitors",
    "ad_id": "120236084000330775",
    "ad_name": "Custom_ audience_Ad_v1",
    "country": "NZ",
    "impressions": 51,
    "clicks": 1,
    "reach": 13,
    "leads": 0,
    "spend": 0.59,
    "level": "ad"
  },
  {
    "date": "2026-02-22",
    "campaign_id": "120236084000340775",
    "campaign_name": "Supy_Facebook_Global_Retargetting_campaign",
    "adset_id": "120236084000350775",
    "adset_name": "Supy_Facebook_Form_openers_and_website_visitors",
    "ad_id": "120236084000330775",
    "ad_name": "Custom_ audience_Ad_v1",
    "country": "OM",
    "impressions": 2355,
    "clicks": 17,
    "reach": 1266,
    "leads": 0,
    "spend": 3.47,
    "level": "ad"
  },
  {
    "date": "2026-02-22",
    "campaign_id": "120236084000340775",
    "campaign_name": "Supy_Facebook_Global_Retargetting_campaign",
    "adset_id": "120236084000350775",
    "adset_name": "Supy_Facebook_Form_openers_and_website_visitors",
    "ad_id": "120236084000330775",
    "ad_name": "Custom_ audience_Ad_v1",
    "country": "SA",
    "impressions": 7168,
    "clicks": 39,
    "reach": 4376,
    "leads": 0,
    "spend": 7.26,
    "level": "ad"
  },
  {
    "date": "2026-02-22",
    "campaign_id": "120236084000340775",
    "campaign_name": "Supy_Facebook_Global_Retargetting_campaign",
    "adset_id": "120236084000350775",
    "adset_name": "Supy_Facebook_Form_openers_and_website_visitors",
    "ad_id": "120236084000330775",
    "ad_name": "Custom_ audience_Ad_v1",
    "country": "AE",
    "impressions": 916,
    "clicks": 9,
    "reach": 391,
    "leads": 0,
    "spend": 4.07,
    "level": "ad"
  },
  {
    "date": "2026-02-22",
    "campaign_id": "120236084000340775",
    "campaign_name": "Supy_Facebook_Global_Retargetting_campaign",
    "adset_id": "120236084000350775",
    "adset_name": "Supy_Facebook_Form_openers_and_website_visitors",
    "ad_id": "120236084000330775",
    "ad_name": "Custom_ audience_Ad_v1",
    "country": "GB",
    "impressions": 104,
    "clicks": 3,
    "reach": 55,
    "leads": 0,
    "spend": 4.33,
    "level": "ad"
  },
  {
    "date": "2026-02-22",
    "campaign_id": "120211055502090775",
    "campaign_name": "Supy_Facebook_Ireland_Leadgen",
    "adset_id": "120237266135990775",
    "adset_name": "LAL_Target_UK_Facebook",
    "ad_id": "120237266135980775",
    "ad_name": "LAL_Target_UK_Facebook_Video_Ad",
    "country": "GB",
    "impressions": 5056,
    "clicks": 37,
    "reach": 3790,
    "leads": 0,
    "spend": 151.71,
    "level": "ad"
  },
  {
    "date": "2026-02-22",
    "campaign_id": "120208097408850775",
    "campaign_name": "Supy_Facebook_GCC_LAL_Leadgen",
    "adset_id": "120237560109240775",
    "adset_name": "Facebook_Morroco_Broad",
    "ad_id": "120237560109230775",
    "ad_name": "LAL_Admin_ Morocco_Facebook_Video_Ad",
    "country": "MA",
    "impressions": 14679,
    "clicks": 148,
    "reach": 10226,
    "leads": 4,
    "spend": 27.16,
    "level": "ad"
  },
  {
    "date": "2026-02-22",
    "campaign_id": "120237739636990775",
    "campaign_name": "Supy_Facebook_Singapore_Meta",
    "adset_id": "120237739637120775",
    "adset_name": "Meta_Singapore_Facebook_Leadgen_Broad",
    "ad_id": "120237739637060775",
    "ad_name": "Interest_Singapore _Facebook_Lead_Ad",
    "country": "SG",
    "impressions": 1057,
    "clicks": 7,
    "reach": 828,
    "leads": 0,
    "spend": 23.16,
    "level": "ad"
  },
  {
    "date": "2026-02-22",
    "campaign_id": "120237780732490775",
    "campaign_name": "Supy_Facebook_Macau_Meta",
    "adset_id": "120237780732480775",
    "adset_name": "Meta_Macau_Facebook_Leadgen_Broad",
    "ad_id": "120237780732500775",
    "ad_name": "Interest_Macau_Facebook_Lead_Ad",
    "country": "MO",
    "impressions": 3761,
    "clicks": 13,
    "reach": 2051,
    "leads": 0,
    "spend": 9.58,
    "level": "ad"
  },
  {
    "date": "2026-02-22",
    "campaign_id": "120237782273820775",
    "campaign_name": "Supy_Facebook_Taiwan_Meta",
    "adset_id": "120237782273810775",
    "adset_name": "Meta_Taiwan_Facebook_Leadgen_Broad",
    "ad_id": "120237782273830775",
    "ad_name": "Interest_ Macau_Facebook_Lead_Ad",
    "country": "TW",
    "impressions": 1603,
    "clicks": 19,
    "reach": 1011,
    "leads": 0,
    "spend": 9.77,
    "level": "ad"
  },
  {
    "date": "2026-02-22",
    "campaign_id": "120237828558300775",
    "campaign_name": "Supy_Facebook_Malaysia_Meta",
    "adset_id": "120237828558310775",
    "adset_name": "Meta_Malaysia_Facebook_Leadgen_Enterprise_Broad",
    "ad_id": "120237828558320775",
    "ad_name": "Meta_Malaysia_Facebook_Leadgen_Enterprise_Broad_ad",
    "country": "MY",
    "impressions": 1605,
    "clicks": 9,
    "reach": 1028,
    "leads": 0,
    "spend": 16.07,
    "level": "ad"
  },
  {
    "date": "2026-02-22",
    "campaign_id": "120208097408850775",
    "campaign_name": "Supy_Facebook_GCC_LAL_Leadgen",
    "adset_id": "120237834526350775",
    "adset_name": "Facebook_Bahrain_LAL",
    "ad_id": "120237834526340775",
    "ad_name": "Facebook_Bahrain_LAL_ad",
    "country": "BH",
    "impressions": 1010,
    "clicks": 7,
    "reach": 632,
    "leads": 0,
    "spend": 8.88,
    "level": "ad"
  },
  {
    "date": "2026-02-22",
    "campaign_id": "120237959815840775",
    "campaign_name": "Supy_Facebook_Philippines_Meta",
    "adset_id": "120237959815830775",
    "adset_name": "Meta_Philippines_Facebook_Leadgen_Enterprise_Broad",
    "ad_id": "120237959815820775",
    "ad_name": "Interest_Philippines_Facebook_Lead_Ad",
    "country": "PH",
    "impressions": 2377,
    "clicks": 58,
    "reach": 1900,
    "leads": 4,
    "spend": 9.75,
    "level": "ad"
  },
  {
    "date": "2026-02-22",
    "campaign_id": "120208097408850775",
    "campaign_name": "Supy_Facebook_GCC_LAL_Leadgen",
    "adset_id": "120238406407430775",
    "adset_name": "Facebook_Qatar_Broad",
    "ad_id": "120238406407440775",
    "ad_name": "LAL_Admin_Qatar_Facebook_Video_Ad",
    "country": "QA",
    "impressions": 1354,
    "clicks": 6,
    "reach": 867,
    "leads": 0,
    "spend": 12.51,
    "level": "ad"
  },
  {
    "date": "2026-02-22",
    "campaign_id": "120208097408850775",
    "campaign_name": "Supy_Facebook_GCC_LAL_Leadgen",
    "adset_id": "120238406497780775",
    "adset_name": "Facebook_Oman_Broad",
    "ad_id": "120238406497910775",
    "ad_name": "LAL_Admin_Oman_Facebook_Video_Ad",
    "country": "OM",
    "impressions": 1528,
    "clicks": 14,
    "reach": 939,
    "leads": 0,
    "spend": 9.78,
    "level": "ad"
  },
  {
    "date": "2026-02-22",
    "campaign_id": "120208097408850775",
    "campaign_name": "Supy_Facebook_GCC_LAL_Leadgen",
    "adset_id": "120238406566790775",
    "adset_name": "Facebook_Kuwait_Broad",
    "ad_id": "120238406566570775",
    "ad_name": "LAL_Admin_Kuwait_Facebook_Video_Ad",
    "country": "KW",
    "impressions": 1078,
    "clicks": 7,
    "reach": 773,
    "leads": 0,
    "spend": 9.64,
    "level": "ad"
  },
  {
    "date": "2026-02-22",
    "campaign_id": "120211055502090775",
    "campaign_name": "Supy_Facebook_Ireland_Leadgen",
    "adset_id": "120238406899180775",
    "adset_name": "Facebook_UK_Scotland_LAL",
    "ad_id": "120238406899190775",
    "ad_name": "LAL_Deal_UK_Scotland_Facebook_Video_Ad",
    "country": "GB",
    "impressions": 778,
    "clicks": 7,
    "reach": 635,
    "leads": 0,
    "spend": 22.82,
    "level": "ad"
  },
  {
    "date": "2026-02-22",
    "campaign_id": "120211055502090775",
    "campaign_name": "Supy_Facebook_Ireland_Leadgen",
    "adset_id": "120238470739920775",
    "adset_name": "Facebook_Ireland_Broad",
    "ad_id": "120238470739930775",
    "ad_name": "Facebook_Ireland_Broad_ad",
    "country": "IE",
    "impressions": 1470,
    "clicks": 14,
    "reach": 980,
    "leads": 0,
    "spend": 23.78,
    "level": "ad"
  }
]